Workbook
Name AccrualsTemplate: "Button 12"
Name AcquirerAFTFees: [1]Schedules!#REF!
Name AcquirerFeeOptions: [1]Automation!#REF!
Name AcquirerOCTFees: [1]Schedules!#REF!
Name Activity: "Button 59"
Name AddressNoticeAddress: [1]Automation!#REF!
Name AFT: '[1]Dropdown Logic'!$AM$5:$AM$13
Name ApprovalRoute: '[1]MI Database Template'!$P$9:$P$14
Name dcDaysInWeek: 7
Name dcDaysInYear: 365
Name dcMthsInQtr: 3
Name dcMthsInYear: 12
Name dcQtrsInYear: 4
Name dcWeeksInYear: 52
Name DetailedOpenPurchaseOrderListing: "Button 11"
Name DetailedTransactionListings: "Button 9"
Name dMthsInYear: 12
Name FastTrack: [1]Automation!#REF!
Name GraphCumulativeSpend: "Button 5"
Name GraphPhasedSpend: "Button 3"
Name GraphYTDSpendByCategory: "Button 6"
Name HeadlineCategory: "Button 2"
Name Incentive_Options: 'P&L'!$E$109:$E$114
Name Last_Row: #N/A
Name Model: '[2]1b) Forecast Inputs '!$C$4
Name NoticeAddress: [1]Automation!#REF!
Name Number_of_Payments: #N/A
Name OCT: '[1]Dropdown Logic'!$AN$5:$AN$21
Name Payment_Date: #N/A
Name Phased: "Button 61"
Name PhasedReportsActByAccount: "Button 8"
Name Print_Area_Reset: #N/A
Name rtrtrr: #N/A
Name ss: #N/A
Name StrategicPricingPresent: [1]Automation!#REF!
Name TableName: "Dummy"
Name TM1REBUILDOPTION: 0
Name Values_Entered: #N/A
Name VersNo: 0.22
Name YTDVarianceKey: "Object 4"

Sheet Intro
A1: Model Version | C1: ='[1]Change Control'!C13 -> vMar25
B2: Please fill all cells in Yellow | D2: Opportunity ID (OPP-000XXXXXX) | E2: OPP-000989103 | F2: Deal Owner (AE) | G2: Joke Smit | H2: Scenario Name | I2: MLS | K2: Deal Checks Please ensure all checks are green | N2: Include Reason if exception
B3: Client Name | C3: RBI group | D3: Primary Market | E3: Austria | F3: Cluster | G3: =IFERROR(VLOOKUP($E$3,'[1]Deals Database'!$B$12:$C$60,2,0),"") -> Central Europe | H3: CI Ref (Finance to complete) | I3: FY26_331
B5: RBI Group, a traditional bank serving clients across multiple markets with ~7.5 million retail customers, aims to stay competitive in consumer payments. Visa made a proactive offer in FY25 to drive and support early adoption of Visa Direct to card (OCT & AFT) and Visa+ origination for consumer usecases like remittance and top ups. RBI has since provided an updated forecast and requested increased fixed support for development in FY26 and commercial rollout in FY27. The renewed proposal is designed to meet client demand, lock in solution launches across markets, drive XB performance. With this contract we'd win volume from and grow against Wise, Paypal, WeRo etc. | K5: Within Fast Track | L5: =IF(COUNTIF($L$7:$L$15,"No")>0,"No","Yes") -> Yes
B6: Alignment with VE Corporate goals: (How does this deal support VE’s corporate goals? )
B7: This approach aligns with Visa's strategic corporate goals and FY26 / FY27 scorecard by securing Visa Direct's origination penetration in the banking segment and expanding the adoption of Visa Direct value-added services such as Visa+, driving improved user experiences and driving usage. Additionally, selling Visa Direct (to Card) supports Visa's goal to diversify revenues beyond traditional consumer payments. | K7: Upfront <=$250K | L7: =IF(-SUM('P&L'!Q34:Q35)*Inputs!$O$1<=250000,"Yes","No") -> Yes
B8: Win / Retain Strategy (What is the sales strategy? - Idea of what the amount and structure of incentives & Client request?) | C8: 0 | D8: 0 | E8: 0 | F8: 0 | G8: 0 | H8: 0 | I8: 0
B9: Following Visa’s proactive FY25 offer, RBI expanded the scope to include domestic flows, revised the XB forecast, and requested higher fixed support committing to centralised development in FY26 and commercial rollout across countries in FY27 of OCT, AFT and Visa+ origination. Visa aims to secure contracting in FY26 and targets funding the fixed support through a mix of Visa Direct and CIA card‑related incentives, supported by coordinated C‑level to operational engagement. This groupdeal approach empowers RBI at central level, which is something Visa and key RBI staeholders look to establish since long. | K9: Incentive Earn-Through and Contribution B/E by Year 3 | L9: =IF(OR(SUM('P&L'!G38:I38)<=0,SUM('P&L'!G75:I75)<1),"Yes","No") -> Yes | Q9: =IF('P&L'!I49>=0,"Yes","No") -> Yes
B10: Key Benefits (What are the key reasons for approval?) | C10: 0 | D10: 0 | E10: 0 | F10: 0 | G10: 0 | H10: 0 | I10: 0
B11: Reasons for approval: this offer fits within Visa Direct fast track modelling KPI's and fast track contracting. Visa benefits are commited commercial rollout of OCT, AFT and Visa+ products with a key bank across multiple markets and growing & winning volumes against competitors like Wise. The offer stimulates XB performance through tiered transactional XB support and enhances focus on implementation and activation through milestone based fixed support that protects Visa's interests. | K11: Discount on Core Fees <=35% | L11: =IF(-'P&L'!C29<=35%,"Yes","No") -> Yes
B12: Key Commercial Concerns (What are the key concerns about this opportunity?)
B13: RBI has an remittance partnership with Wise in some markets. Not approving this deal will risk volumes going to Wise. One senior stakeholder is known to have a appreciation for Wise, which may influence internal discussions. In addition, RBI’s organisational complexity and resource constraints—similar to other large group banks such as Erste or ING—create to be expected risks in eg execution including possible shifts in timelines or scope despite Visa’s support. Tight project governance and continued alignment on scope, timelines, and resourcing will be essential to mitigate delivery risks and avoid delays. | K13: Total Incenitves excl. IRR VAT < $10M | L13: =IF(-('P&L'!Q33-'P&L'!Q39)<10000000/Inputs!O1,"Yes","No") -> Yes | N13: Provide exception why this deal should be within Fast Track
B14: What other factors should be considered? (Concerns about the client?) | C14: 0 | D14: 0 | E14: 0 | F14: 0 | G14: 0 | H14: 0 | I14: 0
B15: RBI’s geographical scale offers strong strategic upside potential for Visa, This contract will have an signal effect to other bankingclients like Erste Bank, ING. As RBI internal rules currently do not allow to do XB P2P card based payments into all XB corridors - once lifted this could lead to increased inter levels. However, capturing this deal and value requires careful navigation of their multi‑layered decision processes and expectations around support. | K15: Upfront < 25% of Total Incentives | L15: =IF(-'P&L'!Q34<=-SUM('P&L'!Q34:Q38)*0.25,"Yes","No") -> Yes
B17: Please complete the following for Contract Management: | F17: Please complete the following Client information: | K17: Please complete the following information on client's existing business:
B18: Deal Term | D18: 5 | E18: =IF(D18="","Mandatory","") | F18: Client Full Name | H18: RAIFFEISEN BANK INTERNATIONAL AG | K18: Existing CIA with the client? | N18: Yes
B19: Any existing VD portfolio under contract? | D19: No | F19: Client Address | H19: AM STADTPARK 9 | K19: PIF submitted? | N19: No
B20: If existing, when does the contract end? | D20: 47939 | E20: Ukraine only | F20: Client Notice Address | K20: Client live with VDC? | N20: Both AFT & OCT
B21: Start Date for the new deal (qtr beginning) | D21: 46296 | E21: =IF(D21="","Mandatory","") | F21: CW Number | K21: Existing OCT_L12 months (€ PV) | N21: =1589453921.49/1.1734 -> 1.3545713e+09 | O21: countries live: AT, UA, Slovakia, Kosovo, Poland, Albania,
B22: End Date for the new deal (qtr ending) | D22: =IFERROR(EOMONTH(D21-1,'P&L'!C15*12),"") -> 48121 | F22: FY Number | H22: =I3 -> FY26_331 | K22: Existing OCT_L12 months (Txn count) | N22: 33724526
B23: Break clause year (if any) | D23: 0 | F23: BID Identifier | H23: V10069913 | K23: Existing AFT_L12 months (€ PV) | N23: =2934104084.81/1.1734 -> 2.5005148e+09 | O23: countries live: AT, UA, Slovakia, Kosovo, Poland, Albania, Czech Republic
K24: Existing AFT_L12 months (Txn count) | N24: 59,876,805
B25: Microsoft Dynamics Ref (OPP-000XXXXXX) | D25: =E2 -> OPP-000989103
B26: Market Name (or Pan EU)? | D26: =Intro!E3 -> Austria
B29: Sharepoint folder link for model and VDDR deck: | E29: https://visainc.sharepoint.com/:f:/r/sites/VDWPricingTemplateGroup/Shared%20Documents/AE%20Intake%20Form%20(VDC)?csf=1&web=1&e=shDlBz
B30: Link for AFT Money Load Program | E30: https://visa.highspot.com/items/64b7ed48d004140237384d7a
B31: Link for OCT Strategic Alliance Fee Program | E31: https://visa.highspot.com/items/64b7ed7e2b4f9c04ea94b456

Sheet Inputs
A1: EEA | B1: INTRA EEA | D1: Modelling Assumptions | F1: Mandatory Fields | J1: Optional Fields | N1: FX EUR/USD | O1: 1.1734 | R1: Guidance on completing input sheet: 1. Please fill in cells highlighted in Yellow - INPUT in EUROS 2. Please select the Market from the drop down. If multiple markets, please select the biggest market for the opportunity. 3. UK/IS/CH/TK to rest of EU is Intra NON-EEA Transaction (also vice versa). If modelling for UK/IS/CH/TK, there will not be any Intra EEA transactions.
A2: UK | B2: Intra NonEEA
A3: Turkey | F3: Origin Market | G3: =VLOOKUP(Intro!$E$3,[1]Metrics!$B$114:$D$156,3,0) -> EEA | H3: Term | I3: =Intro!D18 -> 5 | N3: FX EUR/GBP | O3: 0.87268
A4: Israel | F4: Client Type | G4: Originator | H4: AFT IRF | I4: Rack | J4: Please select one option or "Rack"
A5: Switzerland | F5: =IF($G$4="Originator","Input Enabler Name","") -> Input Enabler Name | G5: self acquiring | H5: OCT IRF | I5: Rack | J5: Please select one option or "Rack"
D7: Destination | E7: Average Ticket Size
E8: OCT - PP & AA | F8: OCT - FD | G8: AFT - PP & AA | H8: AFT - FD & LA | I8: Cross Curr % | J8: Credit % | K8: Debit %
A9: =$G$3&D9 -> EEADOM | D9: DOM | E9: 208 | G9: 205 | J9: 0.5 | K9: =1-J9 -> 0.5
A10: =$G$3&D10 -> EEAINTRA EEA | D10: INTRA EEA | E10: 213 | G10: 209 | I10: 0.1 | J10: 0.5 | K10: =1-J10 -> 0.5
A11: =$G$3&D11 -> EEAINTRA Non-EEA | D11: INTRA Non-EEA | E11: 213 | G11: 209 | I11: 0.85 | J11: 0.5 | K11: =1-J11 -> 0.5
A12: =$G$3&D12 -> EEAINTER | D12: INTER | E12: 152 | G12: 150 | I12: 0.65 | J12: 0.5 | K12: =1-J12 -> 0.5
A17: Mapping Table - Do not change/delete | D17: Input Number of Transactions by Jurisdiction in Yellow Cells
E18: =IF(E19<=$I$3,1,0) -> 1 | F18: =IF(F19<=$I$3,1,0) -> 1 | G18: =IF(G19<=$I$3,1,0) -> 1 | H18: =IF(H19<=$I$3,1,0) -> 1 | I18: =IF(I19<=$I$3,1,0) -> 1 | J18: =IF(J19<=$I$3,1,0) -> 0 | K18: =IF(K19<=$I$3,1,0) -> 0 | L18: =IF(L19<=$I$3,1,0) -> 0 | ... O18: =IF(O19<=$I$3,1,0) -> 0
D19: OCT - PP & AA | E19: 1 | F19: 2 | G19: 3 | H19: 4 | I19: 5 | J19: 6 | K19: 7 | L19: 8 | M19: 9 | N19: 10 | O19: Total
D20: Total PV | E20: =SUM(E21:E25) -> 1.4922475e+08 | F20: =SUM(F21:F25) -> 2.3936609e+08 | G20: =SUM(G21:G25) -> 3.9076264e+08 | H20: =SUM(H21:H25) -> 5.5191315e+08 | I20: =SUM(I21:I25) -> 8.0713376e+08 | J20: =SUM(J21:J25) -> 0 | K20: =SUM(K21:K25) -> 0 | L20: =SUM(L21:L25) -> 0 | ... N20: =SUM(N21:N25) -> 0 | O20: =SUM(E20:N20) -> 2.1384004e+09
D21: DOM | E21: =E28*$E9 -> 1.2259826e+08 | F21: =F28*$E9 -> 1.7614036e+08 | G21: =G28*$E9 -> 2.5265703e+08 | H21: =H28*$E9 -> 3.5685278e+08 | I21: =I28*$E9 -> 5.0693678e+08 | J21: =J28*$E9 -> 0 | K21: =K28*$E9 -> 0 | L21: =L28*$E9 -> 0 | ... N21: =N28*$E9 -> 0 | O21: =SUM(E21:N21) -> 1.4151852e+09
D22: INTRA EEA - Euro | E22: =E29*$E10 -> 0 | F22: =F29*$E10 -> 0 | G22: =G29*$E10 -> 0 | H22: =H29*$E10 -> 0 | I22: =I29*$E10 -> 0 | J22: =J29*$E10 -> 0 | K22: =K29*$E10 -> 0 | L22: =L29*$E10 -> 0 | ... N22: =N29*$E10 -> 0 | O22: =SUM(E22:N22) -> 0
D23: INTRA EEA - non Euro | E23: =E30*$E10 -> 0 | F23: =F30*$E10 -> 0 | G23: =G30*$E10 -> 0 | H23: =H30*$E10 -> 0 | I23: =I30*$E10 -> 0 | J23: =J30*$E10 -> 0 | K23: =K30*$E10 -> 0 | L23: =L30*$E10 -> 0 | ... N23: =N30*$E10 -> 0 | O23: =SUM(E23:N23) -> 0
D24: INTRA Non-EEA | E24: =E31*$E11 -> 5089381.2 | F24: =F31*$E11 -> 8386282.3 | G24: =G31*$E11 -> 14100935 | H24: =H31*$E11 -> 19916160 | I24: =I31*$E11 -> 29301651 | J24: =J31*$E11 -> 0 | K24: =K31*$E11 -> 0 | L24: =L31*$E11 -> 0 | ... N24: =N31*$E11 -> 0 | O24: =SUM(E24:N24) -> 76794409
D25: INTER | E25: =E32*$E12 -> 21537105 | F25: =F32*$E12 -> 54839443 | G25: =G32*$E12 -> 1.2400468e+08 | H25: =H32*$E12 -> 1.7514421e+08 | I25: =I32*$E12 -> 2.7089532e+08 | J25: =J32*$E12 -> 0 | K25: =K32*$E12 -> 0 | L25: =L32*$E12 -> 0 | ... N25: =N32*$E12 -> 0 | O25: =SUM(E25:N25) -> 6.4642075e+08
F26: =F27/E27-1 -> 0.65163801 | G26: =G27/F27-1 -> 0.68142857 | H26: =H27/G27-1 -> 0.4124 | I26: =I27/H27-1 -> 0.47125 | R26: Choose Main and Detailed Use Case for OCT P2P | T26: Secondary (BAI) | U26: Tertiary BAI
D27: Total Transactions | E27: =SUM(E28:E32) -> 755000 | F27: =SUM(F28:F32) -> 1246986.7 | G27: =SUM(G28:G32) -> 2096719.1 | H27: =SUM(H28:H32) -> 2961406 | I27: =SUM(I28:I32) -> 4356968.6 | J27: =SUM(J28:J32) -> 0 | K27: =SUM(K28:K32) -> 0 | L27: =SUM(L28:L32) -> 0 | ... N27: =SUM(N28:N32) -> 0 | O27: =SUM(E27:N27) -> 11417080 | P27: =O27/SUM($O$27+$O$42+$O$57) -> 0.76923077
A28: =$G$3&$D$19&D28 -> EEAOCT - PP & AADOM | B28: DOM | D28: DOM | E28: 589414.71 | F28: 846828.67 | G28: 1214697.2 | H28: 1715638.4 | I28: 2437196.1 | O28: =SUM(E28:N28) -> 6803775.1 | R28: Remittances | S28: XB P2P (Back-to-back) | T28: PP | U28: AA
A29: =$G$3&$D$19&D29 -> EEAOCT - PP & AAINTRA EEA - Euro | B29: INTRA EEA - Euro | D29: INTRA EEA - Euro | O29: =SUM(E29:N29) -> 0
A30: =$G$3&$D$19&D30 -> EEAOCT - PP & AAINTRA EEA - non Euro | B30: INTRA EEA - non Euro | D30: INTRA EEA - non Euro | O30: =SUM(E30:N30) -> 0
A31: =$G$3&$D$19&D31 -> EEAOCT - PP & AAINTRA Non-EEA | B31: INTRA Non-EEA | D31: INTRA Non-EEA | E31: 23893.808 | F31: 39372.217 | G31: 66201.571 | H31: 93503.099 | I31: 137566.43 | O31: =SUM(E31:N31) -> 360537.13 | R31: Remittances | S31: XB P2P (Back-to-back) | T31: PP | U31: AA
A32: =$G$3&$D$19&D32 -> EEAOCT - PP & AAINTER | B32: INTER | D32: INTER | E32: 141691.48 | F32: 360785.81 | G32: 815820.25 | H32: 1152264.5 | I32: 1782206.1 | O32: =SUM(E32:N32) -> 4252768.1 | R32: Remittances | S32: XB P2P (Back-to-back) | T32: PP | U32: AA
D34: OCT - FD | E34: 1 | F34: 2 | G34: 3 | H34: 4 | I34: 5 | J34: 6 | K34: 7 | L34: 8 | M34: 9 | N34: 10 | O34: Total | R34: Remittances | S34: XB P2P (Back-to-back) | T34: PP | U34: AA
D35: Total PV | E35: =SUM(E36:E40) -> 0 | F35: =SUM(F36:F40) -> 0 | G35: =SUM(G36:G40) -> 0 | H35: =SUM(H36:H40) -> 0 | I35: =SUM(I36:I40) -> 0 | J35: =SUM(J36:J40) -> 0 | K35: =SUM(K36:K40) -> 0 | L35: =SUM(L36:L40) -> 0 | ... N35: =SUM(N36:N40) -> 0 | O35: =SUM(E35:N35) -> 0 | R35: Remittances | S35: XB Funds Transfer (Send funds to receiver only) | T35: PP | U35: AA
D36: DOM | E36: =E43*$F9 -> 0 | F36: =F43*$F9 -> 0 | G36: =G43*$F9 -> 0 | H36: =H43*$F9 -> 0 | I36: =I43*$F9 -> 0 | J36: =J43*$F9 -> 0 | K36: =K43*$F9 -> 0 | L36: =L43*$F9 -> 0 | ... N36: =N43*$F9 -> 0 | O36: =SUM(E36:N36) -> 0 | R36: Person2Person(P2P) | S36: XB P2P (Back-to-back) | T36: PP | U36: AA
D37: INTRA EEA - Euro | E37: =E44*$F10 -> 0 | F37: =F44*$F10 -> 0 | G37: =G44*$F10 -> 0 | H37: =H44*$F10 -> 0 | I37: =I44*$F10 -> 0 | J37: =J44*$F10 -> 0 | K37: =K44*$F10 -> 0 | L37: =L44*$F10 -> 0 | ... N37: =N44*$F10 -> 0 | O37: =SUM(E37:N37) -> 0 | R37: Person2Person(P2P) | S37: Wallet Transfers | T37: WT
D38: INTRA EEA - non Euro | E38: =E45*$F10 -> 0 | F38: =F45*$F10 -> 0 | G38: =G45*$F10 -> 0 | H38: =H45*$F10 -> 0 | I38: =I45*$F10 -> 0 | J38: =J45*$F10 -> 0 | K38: =K45*$F10 -> 0 | L38: =L45*$F10 -> 0 | ... N38: =N45*$F10 -> 0 | O38: =SUM(E38:N38) -> 0 | R38: Person2Person(P2P) | S38: Money Transfers
D39: INTRA Non-EEA | E39: =E46*$F11 -> 0 | F39: =F46*$F11 -> 0 | G39: =G46*$F11 -> 0 | H39: =H46*$F11 -> 0 | I39: =I46*$F11 -> 0 | J39: =J46*$F11 -> 0 | K39: =K46*$F11 -> 0 | L39: =L46*$F11 -> 0 | ... N39: =N46*$F11 -> 0 | O39: =SUM(E39:N39) -> 0
D40: INTER | E40: =E47*$F12 -> 0 | F40: =F47*$F12 -> 0 | G40: =G47*$F12 -> 0 | H40: =H47*$F12 -> 0 | I40: =I47*$F12 -> 0 | J40: =J47*$F12 -> 0 | K40: =K47*$F12 -> 0 | L40: =L47*$F12 -> 0 | ... N40: =N47*$F12 -> 0 | O40: =SUM(E40:N40) -> 0
R41: Choose Main and Detailed Use Case for OCT FD | T41: Secondary (BAI) | U41: Tertiary BAI
D42: Total Transactions | E42: =SUM(E43:E47) -> 0 | F42: =SUM(F43:F47) -> 0 | G42: =SUM(G43:G47) -> 0 | H42: =SUM(H43:H47) -> 0 | I42: =SUM(I43:I47) -> 0 | J42: =SUM(J43:J47) -> 0 | K42: =SUM(K43:K47) -> 0 | L42: =SUM(L43:L47) -> 0 | ... N42: =SUM(N43:N47) -> 0 | O42: =SUM(E42:N42) -> 0 | P42: =O42/SUM($O$27+$O$42+$O$57) -> 0
A43: =$G$3&$D$34&D43 -> EEAOCT - FDDOM | B43: DOM | D43: DOM | O43: =SUM(E43:N43) -> 0
A44: =$G$3&$D$34&D44 -> EEAOCT - FDINTRA EEA - Euro | B44: INTRA EEA - Euro | D44: INTRA EEA - Euro | O44: =SUM(E44:N44) -> 0
A45: =$G$3&$D$34&D45 -> EEAOCT - FDINTRA EEA - non Euro | B45: INTRA EEA - non Euro | D45: INTRA EEA - non Euro | O45: =SUM(E45:N45) -> 0
A46: =$G$3&$D$34&D46 -> EEAOCT - FDINTRA Non-EEA | B46: INTRA Non-EEA | D46: INTRA Non-EEA | O46: =SUM(E46:N46) -> 0
A47: =$G$3&$D$34&D47 -> EEAOCT - FDINTER | B47: INTER | D47: INTER | O47: =SUM(E47:N47) -> 0
F48: =F49/E49-1 -> 1 | G48: =G49/F49-1 -> 0.5 | H48: =H49/G49-1 -> 0.33333333 | I48: =I49/H49-1 -> 0.25
D49: AFT - PP & AA | E49: 1 | F49: 2 | G49: 3 | H49: 4 | I49: 5 | J49: 6 | K49: 7 | L49: 8 | M49: 9 | N49: 10 | O49: Total
D50: Total PV | E50: =SUM(E51:E55) -> 46523100 | F50: =SUM(F51:F55) -> 76839320 | G50: =SUM(G51:G55) -> 1.2919983e+08 | H50: =SUM(H51:H55) -> 1.8248184e+08 | I50: =SUM(I51:I55) -> 2.684764e+08 | J50: =SUM(J51:J55) -> 0 | K50: =SUM(K51:K55) -> 0 | L50: =SUM(L51:L55) -> 0 | ... N50: =SUM(N51:N55) -> 0 | O50: =SUM(E50:N50) -> 7.0352049e+08
D51: DOM | E51: =E58*$G9 -> 41789250 | F51: =F58*$G9 -> 69020714 | G51: =G58*$G9 -> 1.160534e+08 | H51: =H58*$G9 -> 1.6391382e+08 | I51: =I58*$G9 -> 2.4115821e+08 | J51: =J58*$G9 -> 0 | K51: =K58*$G9 -> 0 | L51: =L58*$G9 -> 0 | ... N51: =N58*$G9 -> 0 | O51: =SUM(E51:N51) -> 6.319354e+08
D52: INTRA EEA - Euro | E52: =E59*$G10 -> 0 | F52: =F59*$G10 -> 0 | G52: =G59*$G10 -> 0 | H52: =H59*$G10 -> 0 | I52: =I59*$G10 -> 0 | J52: =J59*$G10 -> 0 | K52: =K59*$G10 -> 0 | L52: =L59*$G10 -> 0 | ... N52: =N59*$G10 -> 0 | O52: =SUM(E52:N52) -> 0
D53: INTRA EEA - non Euro | E53: =E60*$G10 -> 0 | F53: =F60*$G10 -> 0 | G53: =G60*$G10 -> 0 | H53: =H60*$G10 -> 0 | I53: =I60*$G10 -> 0 | J53: =J60*$G10 -> 0 | K53: =K60*$G10 -> 0 | L53: =L60*$G10 -> 0 | ... N53: =N60*$G10 -> 0 | O53: =SUM(E53:N53) -> 0
D54: INTRA Non-EEA | E54: =E61*$G11 -> 4733850 | F54: =F61*$G11 -> 7818606.6 | G54: =G61*$G11 -> 13146428 | H54: =H61*$G11 -> 18568016 | I54: =I61*$G11 -> 27318193 | J54: =J61*$G11 -> 0 | K54: =K61*$G11 -> 0 | L54: =L61*$G11 -> 0 | ... N54: =N61*$G11 -> 0 | O54: =SUM(E54:N54) -> 71585094
D55: INTER | E55: =E62*$G12 -> 0 | F55: =F62*$G12 -> 0 | G55: =G62*$G12 -> 0 | H55: =H62*$G12 -> 0 | I55: =I62*$G12 -> 0 | J55: =J62*$G12 -> 0 | K55: =K62*$G12 -> 0 | L55: =L62*$G12 -> 0 | ... N55: =N62*$G12 -> 0 | O55: =SUM(E55:N55) -> 0
F56: =F57/E57-1 -> 0.65163801 | G56: =G57/F57-1 -> 0.68142857 | H56: =H57/G57-1 -> 0.4124 | I56: =I57/H57-1 -> 0.47125 | R56: Choose Main and Detailed Use Case for AFT | T56: Secondary (BAI) | U56: Tertiary BAI
D57: Total Transactions | E57: =SUM(E58:E62) -> 226500 | F57: =SUM(F58:F62) -> 374096.01 | G57: =SUM(G58:G62) -> 629015.72 | H57: =SUM(H58:H62) -> 888421.8 | I57: =SUM(I58:I62) -> 1307090.6 | J57: =SUM(J58:J62) -> 0 | K57: =SUM(K58:K62) -> 0 | L57: =SUM(L58:L62) -> 0 | ... N57: =SUM(N58:N62) -> 0 | O57: =SUM(E57:N57) -> 3425124.1 | P57: =O57/SUM($O$27+$O$42+$O$57) -> 0.23076923
A58: =$G$3&$D$49&D58 -> EEAAFT - PP & AADOM | B58: DOM | D58: DOM | E58: 203850 | F58: 336686.41 | G58: 566114.14 | H58: 799579.62 | I58: 1176381.5 | O58: =SUM(E58:N58) -> 3082611.7 | R58: Person2Person(P2P) | S58: Money Transfers | T58: PP | U58: AA
A59: =$G$3&$D$49&D59 -> EEAAFT - PP & AAINTRA EEA - Euro | B59: INTRA EEA - Euro | D59: INTRA EEA - Euro | O59: =SUM(E59:N59) -> 0
A60: =$G$3&$D$49&D60 -> EEAAFT - PP & AAINTRA EEA - non Euro | B60: INTRA EEA - non Euro | D60: INTRA EEA - non Euro | O60: =SUM(E60:N60) -> 0
A61: =$G$3&$D$49&D61 -> EEAAFT - PP & AAINTRA Non-EEA | B61: INTRA Non-EEA | D61: INTRA Non-EEA | E61: 22650 | F61: 37409.601 | G61: 62901.572 | H61: 88842.18 | I61: 130709.06 | O61: =SUM(E61:N61) -> 342512.41 | R61: Person2Person(P2P) | S61: Money Transfers
A62: =$G$3&$D$49&D62 -> EEAAFT - PP & AAINTER | B62: INTER | D62: INTER | O62: =SUM(E62:N62) -> 0
D64: AFT - FD & LA | E64: 1 | F64: 2 | G64: 3 | H64: 4 | I64: 5 | J64: 6 | K64: 7 | L64: 8 | M64: 9 | N64: 10 | O64: Total
D65: Total PV | E65: =SUM(E66:E69) -> 0 | F65: =SUM(F66:F69) -> 0 | G65: =SUM(G66:G69) -> 0 | H65: =SUM(H66:H69) -> 0 | I65: =SUM(I66:I69) -> 0 | J65: =SUM(J66:J69) -> 0 | K65: =SUM(K66:K69) -> 0 | L65: =SUM(L66:L69) -> 0 | ... N65: =SUM(N66:N69) -> 0 | O65: =SUM(E65:N65) -> 0
D66: DOM | E66: =E72*$H9 -> 0 | F66: =F72*$H9 -> 0 | G66: =G72*$H9 -> 0 | H66: =H72*$H9 -> 0 | I66: =I72*$H9 -> 0 | J66: =J72*$H9 -> 0 | K66: =K72*$H9 -> 0 | L66: =L72*$H9 -> 0 | ... N66: =N72*$H9 -> 0 | O66: =SUM(E66:N66) -> 0
D67: INTRA EEA | E67: =E73*$H10 -> 0 | F67: =F73*$H10 -> 0 | G67: =G73*$H10 -> 0 | H67: =H73*$H10 -> 0 | I67: =I73*$H10 -> 0 | J67: =J73*$H10 -> 0 | K67: =K73*$H10 -> 0 | L67: =L73*$H10 -> 0 | ... N67: =N73*$H10 -> 0 | O67: =SUM(E67:N67) -> 0
D68: INTRA Non-EEA | E68: =E74*$H11 -> 0 | F68: =F74*$H11 -> 0 | G68: =G74*$H11 -> 0 | H68: =H74*$H11 -> 0 | I68: =I74*$H11 -> 0 | J68: =J74*$H11 -> 0 | K68: =K74*$H11 -> 0 | L68: =L74*$H11 -> 0 | ... N68: =N74*$H11 -> 0 | O68: =SUM(E68:N68) -> 0
D69: INTER | E69: =E75*$H12 -> 0 | F69: =F75*$H12 -> 0 | G69: =G75*$H12 -> 0 | H69: =H75*$H12 -> 0 | I69: =I75*$H12 -> 0 | J69: =J75*$H12 -> 0 | K69: =K75*$H12 -> 0 | L69: =L75*$H12 -> 0 | ... N69: =N75*$H12 -> 0 | O69: =SUM(E69:N69) -> 0
R70: Choose Main and Detailed Use Case for AFT | T70: Secondary (BAI) | U70: Tertiary BAI
D71: Total Transactions | E71: =SUM(E72:E75) -> 0 | F71: =SUM(F72:F75) -> 0 | G71: =SUM(G72:G75) -> 0 | H71: =SUM(H72:H75) -> 0 | I71: =SUM(I72:I75) -> 0 | J71: =SUM(J72:J75) -> 0 | K71: =SUM(K72:K75) -> 0 | L71: =SUM(L72:L75) -> 0 | ... N71: =SUM(N72:N75) -> 0 | O71: =SUM(E71:N71) -> 0 | P71: =O71/SUM($O$27+$O$42+$O$57) -> 0
A72: =$G$3&$D$64&D72 -> EEAAFT - FD & LADOM | B72: DOM | D72: DOM | O72: =SUM(E72:N72) -> 0
A73: =$G$3&$D$64&D73 -> EEAAFT - FD & LAINTRA EEA | B73: INTRA EEA | D73: INTRA EEA | O73: =SUM(E73:N73) -> 0
A74: =$G$3&$D$64&D74 -> EEAAFT - FD & LAINTRA Non-EEA | B74: INTRA Non-EEA | D74: INTRA Non-EEA | O74: =SUM(E74:N74) -> 0
A75: =$G$3&$D$64&D75 -> EEAAFT - FD & LAINTER | B75: INTER | D75: INTER | O75: =SUM(E75:N75) -> 0
D77: Total | E77: 1 | F77: 2 | G77: 3 | H77: 4 | I77: 5 | J77: 6 | K77: 7 | L77: 8 | M77: 9 | N77: 10 | O77: Total
D78: Total PV | E78: =SUM(E79:E82) -> 1.9574785e+08 | F78: =SUM(F79:F82) -> 3.1620541e+08 | G78: =SUM(G79:G82) -> 5.1996247e+08 | H78: =SUM(H79:H82) -> 7.3439499e+08 | I78: =SUM(I79:I82) -> 1.0756102e+09 | J78: =SUM(J79:J82) -> 0 | K78: =SUM(K79:K82) -> 0 | L78: =SUM(L79:L82) -> 0 | ... N78: =SUM(N79:N82) -> 0 | O78: =SUM(E78:N78) -> 2.8419209e+09
D79: DOM | E79: =E51+E36+E21+E66 -> 1.6438751e+08 | F79: =F51+F36+F21+F66 -> 2.4516108e+08 | G79: =G51+G36+G21+G66 -> 3.6871042e+08 | H79: =H51+H36+H21+H66 -> 5.207666e+08 | I79: =I51+I36+I21+I66 -> 7.48095e+08 | J79: =J51+J36+J21+J66 -> 0 | K79: =K51+K36+K21+K66 -> 0 | L79: =L51+L36+L21+L66 -> 0 | ... N79: =N51+N36+N21+N66 -> 0 | O79: =SUM(E79:N79) -> 2.0471206e+09
A80: =$G$3&$D$77&D85 -> EEATotalDOM | B80: DOM | D80: INTRA EEA | E80: =SUM(E22:E23,E37:E38,E52:E53,E67) -> 0 | F80: =SUM(F22:F23,F37:F38,F52:F53,F67) -> 0 | G80: =SUM(G22:G23,G37:G38,G52:G53,G67) -> 0 | H80: =SUM(H22:H23,H37:H38,H52:H53,H67) -> 0 | I80: =SUM(I22:I23,I37:I38,I52:I53,I67) -> 0 | J80: =SUM(J22:J23,J37:J38,J52:J53,J67) -> 0 | K80: =SUM(K22:K23,K37:K38,K52:K53,K67) -> 0 | L80: =SUM(L22:L23,L37:L38,L52:L53,L67) -> 0 | ... N80: =SUM(N22:N23,N37:N38,N52:N53,N67) -> 0 | O80: =SUM(E80:N80) -> 0 | P80: =O85/$O$84 -> 0.66609962
A81: =$G$3&$D$77&D86 -> EEATotalINTRA EEA | B81: INTRA EEA | D81: INTRA Non-EEA | E81: =E54+E39+E24+E68 -> 9823231.2 | F81: =F54+F39+F24+F68 -> 16204889 | G81: =G54+G39+G24+G68 -> 27247363 | H81: =H54+H39+H24+H68 -> 38484176 | I81: =I54+I39+I24+I68 -> 56619843 | J81: =J54+J39+J24+J68 -> 0 | K81: =K54+K39+K24+K68 -> 0 | L81: =L54+L39+L24+L68 -> 0 | ... N81: =N54+N39+N24+N68 -> 0 | O81: =SUM(E81:N81) -> 1.483795e+08 | P81: =O86/$O$84 -> 0
A82: =$G$3&$D$77&D87 -> EEATotalINTRA Non-EEA | B82: INTRA Non-EEA | D82: INTER | E82: =E55+E40+E25+E69 -> 21537105 | F82: =F55+F40+F25+F69 -> 54839443 | G82: =G55+G40+G25+G69 -> 1.2400468e+08 | H82: =H55+H40+H25+H69 -> 1.7514421e+08 | I82: =I55+I40+I25+I69 -> 2.7089532e+08 | J82: =J55+J40+J25+J69 -> 0 | K82: =K55+K40+K25+K69 -> 0 | L82: =L55+L40+L25+L69 -> 0 | ... N82: =N55+N40+N25+N69 -> 0 | O82: =SUM(E82:N82) -> 6.4642075e+08 | P82: =O87/$O$84 -> 0.04736827
A83: =$G$3&$D$77&D88 -> EEATotalINTER | B83: INTER | P83: =O88/$O$84 -> 0.28653211
D84: Grand Total Transactions | E84: =SUM(E85:E88) -> 981500 | F84: =SUM(F85:F88) -> 1621082.7 | G84: =SUM(G85:G88) -> 2725734.8 | H84: =SUM(H85:H88) -> 3849827.8 | I84: =SUM(I85:I88) -> 5664059.1 | J84: =SUM(J85:J88) -> 0 | K84: =SUM(K85:K88) -> 0 | L84: =SUM(L85:L88) -> 0 | ... N84: =SUM(N85:N88) -> 0 | O84: =SUM(E84:N84) -> 14842204
D85: DOM | E85: =E58+E43+E28+E72 -> 793264.71 | F85: =F58+F43+F28+F72 -> 1183515.1 | G85: =G58+G43+G28+G72 -> 1780811.4 | H85: =H58+H43+H28+H72 -> 2515218 | I85: =I58+I43+I28+I72 -> 3613577.6 | J85: =J58+J43+J28+J72 -> 0 | K85: =K58+K43+K28+K72 -> 0 | L85: =L58+L43+L28+L72 -> 0 | ... N85: =N58+N43+N28+N72 -> 0 | O85: =SUM(E85:N85) -> 9886386.8
D86: INTRA EEA | E86: =SUM(E29:E30,E44:E45,E59:E60,E73) -> 0 | F86: =SUM(F29:F30,F44:F45,F59:F60,F73) -> 0 | G86: =SUM(G29:G30,G44:G45,G59:G60,G73) -> 0 | H86: =SUM(H29:H30,H44:H45,H59:H60,H73) -> 0 | I86: =SUM(I29:I30,I44:I45,I59:I60,I73) -> 0 | J86: =SUM(J29:J30,J44:J45,J59:J60,J73) -> 0 | K86: =SUM(K29:K30,K44:K45,K59:K60,K73) -> 0 | L86: =SUM(L29:L30,L44:L45,L59:L60,L73) -> 0 | ... N86: =SUM(N29:N30,N44:N45,N59:N60,N73) -> 0 | O86: =SUM(E86:N86) -> 0
D87: INTRA Non-EEA | E87: =E61+E46+E31+E74 -> 46543.808 | F87: =F61+F46+F31+F74 -> 76781.818 | G87: =G61+G46+G31+G74 -> 129103.14 | H87: =H61+H46+H31+H74 -> 182345.28 | I87: =I61+I46+I31+I74 -> 268275.49 | J87: =J61+J46+J31+J74 -> 0 | K87: =K61+K46+K31+K74 -> 0 | L87: =L61+L46+L31+L74 -> 0 | ... N87: =N61+N46+N31+N74 -> 0 | O87: =SUM(E87:N87) -> 703049.54
D88: INTER | E88: =E62+E47+E32+E75 -> 141691.48 | F88: =F62+F47+F32+F75 -> 360785.81 | G88: =G62+G47+G32+G75 -> 815820.25 | H88: =H62+H47+H32+H75 -> 1152264.5 | I88: =I62+I47+I32+I75 -> 1782206.1 | J88: =J62+J47+J32+J75 -> 0 | K88: =K62+K47+K32+K75 -> 0 | L88: =L62+L47+L32+L75 -> 0 | ... N88: =N62+N47+N32+N75 -> 0 | O88: =SUM(E88:N88) -> 4252768.1
E91: =E84*0.1 -> 98150 | F91: =F84*0.35 -> 567378.95
E92: =E91*AVERAGE([1]Calcs!J7:J81) -> 29518.472
E96: Start Qtr | F96: End Qtr | G96: Rack | H96: Rack
E97: 44562 | F97: 44926 | G97: MLP T1 | H97: Standard - EU - Instant Funding Program Tier 1
E98: 44652 | F98: 45016 | G98: MLP T2 | H98: Standard - EU - Instant Funding Program Tier 2
E99: 44743 | F99: 45107
E100: 44835 | F100: 45199 | G100: Rack | H100: Rack
E101: 44927 | F101: 45291 | G101: SAFP | H101: Standard - EU - Strategic Alliance Fee Programme
E102: 45017 | F102: 45382
E103: 45108 | F103: 45473
E104: 45200 | F104: 45565
E105: 45292 | F105: 45657
E106: 45383 | F106: 45747
E107: 45474 | F107: 45838
E108: 45566 | F108: 45930
E109: 45658 | F109: 46022
E110: 45748 | F110: 46112
E111: 45839 | F111: 46203
E112: 45931 | F112: 46295
E113: 46023 | F113: 46387
...

Sheet P&L
F2: Option 2 (Only XB OCTs, tiered discount) | G2: 0.03 | H2: Option 1: Flat % discount on all core OCT fees (AFTs excluded), Max 35%. For small deals cap at 25% | J2: Option 2: Tiered XB Discount on XB OCTs only (refer to tiering Table) - standard tier table | L2: Option 3: Tiered % Discount on All OCTs, tiering by DOM/Intra and XB | N2: Enterprie Adj. AANR | O2: =(Q41+Q47)/Intro!D18 -> 1224739 | P2: =O2*Inputs!O1 -> 1437108.8 | Q2: EU VD Only Adj. AANR | R2: =SUM(Q19:Q25,Q31,Q33,Q47)/Intro!D18 -> 704788.49 | S2: =R2*Inputs!O1 -> 826998.82
F3: OCT Txn % | G3: =IFERROR(1-G4,"") -> 0.76923077 | H3: =IFERROR(1-H4,"") -> 0.76923077 | I3: =IFERROR(1-I4,"") -> 0.76923077 | J3: =IFERROR(1-J4,"") -> 0.76923077 | K3: =IFERROR(1-K4,"") -> 0.76923077 | L3: =IFERROR(1-L4,"") | M3: =IFERROR(1-M4,"") | N3: =IFERROR(1-N4,"") | P3: =IFERROR(1-P4,"")
C4: =IFERROR(IF(AND(Intro!D22<>"", Intro!D21<>"", C15<>""), IF(ABS(DATEDIF(Intro!D21,Intro!D22,"D") - C15*365.25) > 5, "DATE ERROR",""),""),"Check Start/End Qtr") | F4: AFT Txn % | G4: =IFERROR(Inputs!E57/Inputs!E84,"") -> 0.23076923 | H4: =IFERROR(Inputs!F57/Inputs!F84,"") -> 0.23076923 | I4: =IFERROR(Inputs!G57/Inputs!G84,"") -> 0.23076923 | J4: =IFERROR(Inputs!H57/Inputs!H84,"") -> 0.23076923 | K4: =IFERROR(Inputs!I57/Inputs!I84,"") -> 0.23076923 | L4: =IFERROR(Inputs!J57/Inputs!J84,"") | M4: =IFERROR(Inputs!K57/Inputs!K84,"") | N4: =IFERROR(Inputs!L57/Inputs!L84,"") | ... Q4: =IFERROR(Inputs!O57/Inputs!O84,"") -> 0.23076923
F5: Total | G5: 1 | H5: 2 | I5: 3 | J5: 4 | K5: 5 | L5: 6 | M5: 7 | N5: 8 | O5: 9 | P5: 10 | Q5: Total
F6: PV - Total EUROS | G6: =Inputs!E78 -> 1.9574785e+08 | H6: =Inputs!F78 -> 3.1620541e+08 | I6: =Inputs!G78 -> 5.1996247e+08 | J6: =Inputs!H78 -> 7.3439499e+08 | K6: =Inputs!I78 -> 1.0756102e+09 | L6: =Inputs!J78 -> 0 | M6: =Inputs!K78 -> 0 | N6: =Inputs!L78 -> 0 | ... P6: =Inputs!N78 -> 0 | Q6: =SUM(G6:P6) -> 2.8419209e+09 | S6: =Q6=Q9+Q12+Q15 -> TRUE
F7: Transactions - Total | G7: =Inputs!E84 -> 981500 | H7: =Inputs!F84 -> 1621082.7 | I7: =Inputs!G84 -> 2725734.8 | J7: =Inputs!H84 -> 3849827.8 | K7: =Inputs!I84 -> 5664059.1 | L7: =Inputs!J84 -> 0 | M7: =Inputs!K84 -> 0 | N7: =Inputs!L84 -> 0 | ... P7: =Inputs!N84 -> 0 | Q7: =SUM(G7:P7) -> 14842204 | S7: =Q7=Q10+Q13+Q16 -> TRUE
E9: PV and Volumes | F9: PV - EU Dom | G9: =Inputs!E79 -> 1.6438751e+08 | H9: =Inputs!F79 -> 2.4516108e+08 | I9: =Inputs!G79 -> 3.6871042e+08 | J9: =Inputs!H79 -> 5.207666e+08 | K9: =Inputs!I79 -> 7.48095e+08 | L9: =Inputs!J79 -> 0 | M9: =Inputs!K79 -> 0 | N9: =Inputs!L79 -> 0 | ... P9: =Inputs!N79 -> 0 | Q9: =SUM(G9:P9) -> 2.0471206e+09 | S9: =Q9=Inputs!O79 -> TRUE
F10: Transactions - EU Dom | G10: =Inputs!E85 -> 793264.71 | H10: =Inputs!F85 -> 1183515.1 | I10: =Inputs!G85 -> 1780811.4 | J10: =Inputs!H85 -> 2515218 | K10: =Inputs!I85 -> 3613577.6 | L10: =Inputs!J85 -> 0 | M10: =Inputs!K85 -> 0 | N10: =Inputs!L85 -> 0 | ... P10: =Inputs!N85 -> 0 | Q10: =SUM(G10:P10) -> 9886386.8 | S10: =Q10=Inputs!O85 -> TRUE
F12: PV - EU Intra EEA + Non-EEA | G12: =SUM(Inputs!E80:E81) -> 9823231.2 | H12: =SUM(Inputs!F80:F81) -> 16204889 | I12: =SUM(Inputs!G80:G81) -> 27247363 | J12: =SUM(Inputs!H80:H81) -> 38484176 | K12: =SUM(Inputs!I80:I81) -> 56619843 | L12: =SUM(Inputs!J80:J81) -> 0 | M12: =SUM(Inputs!K80:K81) -> 0 | N12: =SUM(Inputs!L80:L81) -> 0 | ... P12: =SUM(Inputs!N80:N81) -> 0 | Q12: =SUM(G12:P12) -> 1.483795e+08 | S12: =Q12=Inputs!O80+Inputs!O81 -> TRUE
F13: Transactions - EU Intra EEA + Non-EEA | G13: =SUM(Inputs!E86:E87) -> 46543.808 | H13: =SUM(Inputs!F86:F87) -> 76781.818 | I13: =SUM(Inputs!G86:G87) -> 129103.14 | J13: =SUM(Inputs!H86:H87) -> 182345.28 | K13: =SUM(Inputs!I86:I87) -> 268275.49 | L13: =SUM(Inputs!J86:J87) -> 0 | M13: =SUM(Inputs!K86:K87) -> 0 | N13: =SUM(Inputs!L86:L87) -> 0 | ... P13: =SUM(Inputs!N86:N87) -> 0 | Q13: =SUM(G13:P13) -> 703049.54 | S13: =Q13=Inputs!O86+Inputs!O87 -> TRUE
B14: Deal KPIs (EUROS)
B15: Term of Contract (years) | C15: =Inputs!I3 -> 5 | F15: PV - XB | G15: =Inputs!E82 -> 21537105 | H15: =Inputs!F82 -> 54839443 | I15: =Inputs!G82 -> 1.2400468e+08 | J15: =Inputs!H82 -> 1.7514421e+08 | K15: =Inputs!I82 -> 2.7089532e+08 | L15: =Inputs!J82 -> 0 | M15: =Inputs!K82 -> 0 | N15: =Inputs!L82 -> 0 | ... P15: =Inputs!N82 -> 0 | Q15: =SUM(G15:P15) -> 6.4642075e+08 | S15: =Q15=Inputs!O82 -> TRUE
B16: Total Transactions | C16: =Inputs!O84 -> 14842204 | F16: Transactions - XB | G16: =Inputs!E88 -> 141691.48 | H16: =Inputs!F88 -> 360785.81 | I16: =Inputs!G88 -> 815820.25 | J16: =Inputs!H88 -> 1152264.5 | K16: =Inputs!I88 -> 1782206.1 | L16: =Inputs!J88 -> 0 | M16: =Inputs!K88 -> 0 | N16: =Inputs!L88 -> 0 | ... P16: =Inputs!N88 -> 0 | Q16: =SUM(G16:P16) -> 4252768.1 | S16: =Q16=Inputs!O88 -> TRUE
B17: Average Annualised Tranactions | C17: =IFERROR(C16/C15,0) -> 2968440.9
B18: DOM Txn% | C18: =IFERROR(Inputs!P80,"check") -> 0.66609962 | E18: Fees/revenue | F18: Gross Revenue (OCT+AFT) | G18: =SUM(G19:G32) -> 280593.61 | H18: =SUM(H19:H32) -> 703491.34 | I18: =SUM(I19:I32) -> 1394696.8 | J18: =SUM(J19:J32) -> 1861674.8 | K18: =SUM(K19:K32) -> 2846225.9 | L18: =SUM(L19:L32) -> 0 | M18: =SUM(M19:M32) -> 0 | N18: =SUM(N19:N32) -> 0 | ... P18: =SUM(P19:P32) -> 0 | Q18: =SUM(G18:P18) -> 7086682.5
B19: INTRA EEA Txn% | C19: =IFERROR(Inputs!P81,"check") -> 0 | F19: Acq Processing Rev - EU Dom | G19: =[1]Calcs!AY103 -> 835.785 | H19: =[1]Calcs!AZ103 -> 1380.4143 | I19: =[1]Calcs!BA103 -> 2321.068 | J19: =[1]Calcs!BB103 -> 3278.2764 | K19: =[1]Calcs!BC103 -> 4823.1642 | L19: =[1]Calcs!BD103 -> 0 | M19: =[1]Calcs!BE103 -> 0 | N19: =[1]Calcs!BF103 -> 0 | ... P19: =[1]Calcs!BH103 -> 0 | Q19: =SUM(G19:P19) -> 12638.708
B20: INTRA Non-EEA Txn% | C20: =IFERROR(Inputs!P82,"check") -> 0.04736827 | F20: Acq Scheme Rev - EU Dom | G20: =[1]Calcs!AN103 -> 19813.447 | H20: =[1]Calcs!AO103 -> 30824.576 | I20: =[1]Calcs!AP103 -> 48691.552 | J20: =[1]Calcs!AQ103 -> 68771.949 | K20: =[1]Calcs!AR103 -> 99876.676 | L20: =[1]Calcs!AS103 -> 0 | M20: =[1]Calcs!AT103 -> 0 | N20: =[1]Calcs!AU103 -> 0 | ... P20: =[1]Calcs!AW103 -> 0 | Q20: =SUM(G20:P20) -> 267978.2
B21: Inter Txn% | C21: =IFERROR(Inputs!P83,"check") -> 0.28653211
B22: Total Core Acquiring Fees | C22: =SUM(G19:P25) -> 4433619.5 | F22: Acq Processing Rev - EU Intra | G22: =[1]Calcs!AY104 -> 0 | H22: =[1]Calcs!AZ104 -> 0 | I22: =[1]Calcs!BA104 -> 0 | J22: =[1]Calcs!BB104 -> 0 | K22: =[1]Calcs!BC104 -> 0 | L22: =[1]Calcs!BD104 -> 0 | M22: =[1]Calcs!BE104 -> 0 | N22: =[1]Calcs!BF104 -> 0 | ... P22: =[1]Calcs!BH104 -> 0 | Q22: =SUM(G22:P22) -> 0
B23: Total Gross Revenue | C23: =Q18 -> 7086682.5 | F23: Acq Scheme Rev - EU Intra | G23: =[1]Calcs!AN104 -> 0 | H23: =[1]Calcs!AO104 -> 0 | I23: =[1]Calcs!AP104 -> 0 | J23: =[1]Calcs!AQ104 -> 0 | K23: =[1]Calcs!AR104 -> 0 | L23: =[1]Calcs!AS104 -> 0 | M23: =[1]Calcs!AT104 -> 0 | N23: =[1]Calcs!AU104 -> 0 | ... P23: =[1]Calcs!AW104 -> 0 | Q23: =SUM(G23:P23) -> 0
B24: Total Incentives incl IRR VAT | C24: =Q33 -> -850487.43
B25: Total Net Revenue | C25: =IFERROR(Q41,0) -> 6236195.1 | F25: Acquirer Rev - XB (Inter + Intra non EEA) | G25: =SUM([1]Calcs!AN105:AN106,[1]Calcs!AY105:AY106) -> 156748.7 | H25: =SUM([1]Calcs!AO105:AO106,[1]Calcs!AZ105:AZ106) -> 365934.07 | I25: =SUM([1]Calcs!AP105:AP106,[1]Calcs!BA105:BA106) -> 792099.58 | J25: =SUM([1]Calcs!AQ105:AQ106,[1]Calcs!BB105:BB106) -> 1118761.5 | K25: =SUM([1]Calcs!AR105:AR106,[1]Calcs!BC105:BC106) -> 1719458.8 | L25: =SUM([1]Calcs!AS105:AS106,[1]Calcs!BD105:BD106) -> 0 | M25: =SUM([1]Calcs!AT105:AT106,[1]Calcs!BE105:BE106) -> 0 | N25: =SUM([1]Calcs!AU105:AU106,[1]Calcs!BF105:BF106) -> 0 | ... P25: =SUM([1]Calcs!AW105:AW106,[1]Calcs!BH105:BH106) -> 0 | Q25: =SUM(G25:P25) -> 4153002.6 | S25: =SUM(Q20:Q25) -> 4420980.8
B26: AANR | C26: =IFERROR(C25/C15,0) -> 1247239 | F26: Issuer Rev (All Volumes) | G26: =G73 -> 8710.5371 | H26: =H73 -> 11761.468 | I26: =I73 -> 16036.29 | J26: =J73 -> 20384.691 | K26: =K73 -> 26398.67 | L26: =L73 -> 0 | M26: =M73 -> 0 | N26: =N73 -> 0 | ... P26: =P73 -> 0 | Q26: =SUM(G26:P26) -> 83291.657
B27: AANR excl VTS | C27: =(Q41-Q32)/C15 -> 1240388.8 | F27: Other Fees (e.g. Alias Directory) | Q27: =SUM(G27:P27) -> 0
B28: Incentive $ of Gross Rev. incl VAT | C28: =IFERROR(C24/C23,0) -> -0.12001207 | F28: VIK Revenues | G28: =-SUM(G35,G37) -> 0 | H28: =-SUM(H35,H37) -> 75000 | I28: =-SUM(I35,I37) -> 75000 | J28: =-SUM(J35,J37) -> 0 | K28: =-SUM(K35,K37) -> 0 | L28: =-SUM(L35,L37) -> 0 | M28: =-SUM(M35,M37) -> 0 | N28: =-SUM(N35,N37) -> 0 | ... P28: =-SUM(P35,P37) -> 0 | Q28: =SUM(G28:P28) -> 150000
B29: Incentive $ of Core Fees excl IRR VAT | C29: =IFERROR((C24-Q39)/C22,0) -> -0.1875684 | F29: FX Spread - Inter | G29: =[1]Calcs!BJ106 -> 62996.031 | H29: =[1]Calcs!BK106 -> 160405.37 | I29: =[1]Calcs!BL106 -> 362713.68 | J29: =[1]Calcs!BM106 -> 512296.8 | K29: =[1]Calcs!BN106 -> 792368.81 | L29: =[1]Calcs!BO106 -> 0 | M29: =[1]Calcs!BP106 -> 0 | N29: =[1]Calcs!BQ106 -> 0 | ... P29: =[1]Calcs!BS106 -> 0 | Q29: =SUM(G29:P29) -> 1890780.7
B30: IRR VAT Rate | C30: 0.0277 | F30: FX Spread - Intra | G30: =[1]Calcs!BJ104+[1]Calcs!BJ105 -> 29224.113 | H30: =[1]Calcs!BK104+[1]Calcs!BK105 -> 48209.544 | I30: =[1]Calcs!BL104+[1]Calcs!BL105 -> 81060.905 | J30: =[1]Calcs!BM104+[1]Calcs!BM105 -> 114490.42 | K30: =[1]Calcs!BN104+[1]Calcs!BN105 -> 168444.03 | L30: =[1]Calcs!BO104+[1]Calcs!BO105 -> 0 | M30: =[1]Calcs!BP104+[1]Calcs!BP105 -> 0 | N30: =[1]Calcs!BQ104+[1]Calcs!BQ105 -> 0 | ... P30: =[1]Calcs!BS104+[1]Calcs!BS105 -> 0 | Q30: =SUM(G30:P30) -> 441429.02
B31: IRR VAT Rate | C31: 0.0277 | F31: Visa+ | H31: =SUM(Inputs!F27,Inputs!F42)*[1]Calcs!$B$4*0.5 -> 6234.9335 | I31: =SUM(Inputs!G27,Inputs!G42)*[1]Calcs!$B$4*0.5 -> 10483.595 | J31: =SUM(Inputs!H27,Inputs!H42)*[1]Calcs!$B$4*0.5 -> 14807.03 | K31: =SUM(Inputs!I27,Inputs!I42)*[1]Calcs!$B$4*0.5 -> 21784.843 | L31: =SUM(Inputs!J27,Inputs!J42)*[1]Calcs!$B$4*0.5 -> 0 | M31: =SUM(Inputs!K27,Inputs!K42)*[1]Calcs!$B$4*0.5 -> 0 | N31: =SUM(Inputs!L27,Inputs!L42)*[1]Calcs!$B$4*0.5 -> 0 | O31: =SUM(Inputs!M27,Inputs!M42)*[1]Calcs!$B$4*0.5 -> 0 | P31: =SUM(Inputs!N27,Inputs!N42)*[1]Calcs!$B$4*0.5 -> 0 | Q31: =SUM(G31:P31) -> 53310.402 | R31: Visa+ fee waived until 2027
B32: Deal Breakeven | C32: =Q75 -> 1 | F32: Delegated Auth Fees (3DS/VTS) | G32: =SUM(Inputs!E57,Inputs!E71)*[1]Calcs!$B$3 -> 2265 | H32: =SUM(Inputs!F57,Inputs!F71)*[1]Calcs!$B$3 -> 3740.9601 | I32: =SUM(Inputs!G57,Inputs!G71)*[1]Calcs!$B$3 -> 6290.1572 | J32: =SUM(Inputs!H57,Inputs!H71)*[1]Calcs!$B$3 -> 8884.218 | K32: =SUM(Inputs!I57,Inputs!I71)*[1]Calcs!$B$3 -> 13070.906 | L32: =SUM(Inputs!J57,Inputs!J71)*[1]Calcs!$B$3 -> 0 | M32: =SUM(Inputs!K57,Inputs!K71)*[1]Calcs!$B$3 -> 0 | N32: =SUM(Inputs!L57,Inputs!L71)*[1]Calcs!$B$3 -> 0 | ... P32: =SUM(Inputs!N57,Inputs!N71)*[1]Calcs!$B$3 -> 0 | Q32: =SUM(G32:P32) -> 34251.241
B33: Upfront | C33: =Q34+Q35 -> -45000 | E33: Incentives | F33: Total Incentives (incl VAT) | G33: =SUM(G34:G39) -> -46246.5 | H33: =SUM(H34:H39) -> -75000 | I33: =SUM(I34:I39) -> -82075.163 | J33: =SUM(J34:J39) -> -221300.75 | K33: =SUM(K34:K39) -> -425865.02 | L33: =SUM(L34:L39) -> 0 | M33: =SUM(M34:M39) -> 0 | N33: =SUM(N34:N39) -> 0 | ... Q33: =SUM(Q34:Q39) -> -850487.43 | R33: =Q33/Q18 -> -0.12001207 | S33: =Q33/SUM(Q19:Q25) -> -0.19182689
B34: Fixed Support | C34: =Q36+Q37 -> -150000 | F34: Upfront Cash - earned out | G34: -45000 | Q34: =SUM(G34:P34) -> -45000 | R34: end of 2027
F35: Upfront VIK (Gross, including VAT) - earned out | Q35: =SUM(G35:P35) -> 0
B36: Volume Support | C36: =Q38 -> -636606.92 | F36: Fixed Support - earned out | Q36: =SUM(G36:P36) -> 0
B37: Total Incentive Value | C37: =SUM(C33:C36) -> -831606.92 | F37: VIK Support (Gross, including VAT) - earned out | H37: -75000 | I37: -75000 | Q37: =SUM(G37:P37) -> -150000
B38: Please review the RED cells as these indicate an error | F38: Volume Support (milestone based) | G38: =IF(SUM($G$117:G117)-SUM($G34:G$37)>0,0,SUM($G$117:G117)-SUM($G34:G$37)) -> 0 | H38: =IF((SUM($G$117:H117)-SUM($G34:H$37)-SUM($G$38:G38))>0,0,SUM($G$117:H117)-SUM($G34:H$37)-SUM($G38:G38)) -> 0 | I38: =IF((SUM($G$117:I117)-SUM($G34:I$37)-SUM($G$38:H38))>0,0,SUM($G$117:I117)-SUM($G34:I$37)-SUM($G38:H38)) -> -6884.4635 | J38: =IF((SUM($G$117:J117)-SUM($G34:J$37)-SUM($G$38:I38))>0,0,SUM($G$117:J117)-SUM($G34:J$37)-SUM($G38:I38)) -> -215335.94 | K38: =IF((SUM($G$117:K117)-SUM($G34:K$37)-SUM($G$38:J38))>0,0,SUM($G$117:K117)-SUM($G34:K$37)-SUM($G38:J38)) -> -414386.51 | L38: =IF((SUM($G$117:L117)-SUM($G34:L$37)-SUM($G$38:K38))>0,0,SUM($G$117:L117)-SUM($G34:L$37)-SUM($G38:K38)) -> 0 | M38: =IF((SUM($G$117:M117)-SUM($G34:M$37)-SUM($G$38:L38))>0,0,SUM($G$117:M117)-SUM($G34:M$37)-SUM($G38:L38)) -> 0 | N38: =IF((SUM($G$117:N117)-SUM($G34:N$37)-SUM($G$38:M38))>0,0,SUM($G$117:N117)-SUM($G34:N$37)-SUM($G38:M38)) -> 0 | O38: =IF((SUM($G$117:O117)-SUM($G34:O$37)-SUM($G$38:N38))>0,0,SUM($G$117:O117)-SUM($G34:O$37)-SUM($G38:N38)) -> 0 | P38: =IF((SUM($G$117:P117)-SUM($G34:P$37)-SUM($G$38:O38))>0,0,SUM($G$117:P117)-SUM($G34:P$37)-SUM($G38:O38)) -> 0 | Q38: =SUM(G38:P38) -> -636606.92
B39: Select Incetive structure option below Note: All Options include earnout of Upfront, VIK and Fixed Incentives | F39: VAT on Merchant Support | G39: =SUM(G36,G38,G34)*$C$30 -> -1246.5 | H39: =SUM(H36,H38,H34)*$C$30 -> 0 | I39: =SUM(I36,I38,I34)*$C$30 -> -190.69964 | J39: =SUM(J36,J38,J34)*$C$30 -> -5964.8057 | K39: =SUM(K36,K38,K34)*$C$30 -> -11478.506 | L39: =SUM(L36,L38,L34)*$C$30 -> 0 | M39: =SUM(M36,M38,M34)*$C$30 -> 0 | N39: =SUM(N36,N38,N34)*$C$30 -> 0 | ... P39: =SUM(P36,P38,P34)*$C$30 -> 0 | Q39: =SUM(G39:P39) -> -18880.512
E41: Net Revenue | G41: =G18+G33 -> 234347.11 | H41: =H18+H33 -> 628491.34 | I41: =I18+I33 -> 1312621.7 | J41: =J18+J33 -> 1640374.1 | K41: =K18+K33 -> 2420360.9 | L41: =L18+L33 -> 0 | M41: =M18+M33 -> 0 | N41: =N18+N33 -> 0 | ... P41: =P18+P33 -> 0 | Q41: =SUM(G41:P41) -> 6236195.1
E42: Cumulative Net Revenue | G42: =G41 -> 234347.11 | H42: =G42+H41 -> 862838.45 | I42: =H42+I41 -> 2175460.1 | J42: =I42+J41 -> 3815834.2 | K42: =J42+K41 -> 6236195.1 | L42: =K42+L41 -> 6236195.1 | M42: =L42+M41 -> 6236195.1 | N42: =M42+N41 -> 6236195.1 | O42: =N42+O41 -> 6236195.1 | P42: =O42+P41 -> 6236195.1 | Q42: =Q41 -> 6236195.1
E44: Variable Costs | G44: =G45+G46+G47 -> -2574.4745 | H44: =H45+H46+H47 -> -60173.02 | I44: =I45+I46+I47 -> -62431.966 | J44: =J45+J46+J47 -> -8257.8806 | K44: =K45+K46+K47 -> -11554.681 | L44: =L45+L46+L47 -> 0 | M44: =M45+M46+M47 -> 0 | N44: =N45+N46+N47 -> 0 | ... P44: =P45+P46+P47 -> 0 | Q44: =SUM(G44:P44) -> -144992.02
F45: Auth | G45: =-G$7*G$64 -> -1370.6357 | H45: =-H$7*H$64 -> -2088.5938 | I45: =-I$7*I$64 -> -3291.2441 | J45: =-J$7*J$64 -> -4396.4491 | K45: =-K$7*K$64 -> -6151.6469 | L45: =-L$7*L$64 -> 0 | M45: =-M$7*M$64 -> 0 | N45: =-N$7*N$64 -> 0 | ... P45: =-P$7*P$64 -> 0 | Q45: =SUM(G45:P45) -> -17298.57
F46: C&S | G46: =-G$7*G$65 -> -1203.8388 | H46: =-H$7*H$65 -> -1834.4263 | I46: =-I$7*I$65 -> -2890.7223 | J46: =-J$7*J$65 -> -3861.4315 | K46: =-K$7*K$65 -> -5403.0338 | L46: =-L$7*L$65 -> 0 | M46: =-M$7*M$65 -> 0 | N46: =-N$7*N$65 -> 0 | ... P46: =-P$7*P$65 -> 0 | Q46: =SUM(G46:P46) -> -15193.453 | S46: =0.034*0.8 -> 0.0272
B47: =SUM($G$117:H117)-SUM($G34:H$37)-SUM($G$38:G38) -> 70576.556 | E47: 0.75 | F47: VIK Costs | G47: =-G28*$E$47 -> 0 | H47: =-H28*$E$47 -> -56250 | I47: =-I28*$E$47 -> -56250 | J47: =-J28*$E$47 -> 0 | K47: =-K28*$E$47 -> 0 | L47: =-L28*$E$47 -> 0 | M47: =-M28*$E$47 -> 0 | N47: =-N28*$E$47 -> 0 | ... P47: =-P28*$E$47 -> 0 | Q47: =SUM(G47:P47) -> -112500 | S47: 0.025
E48: Contribution | G48: =G44+G41 -> 231772.64 | H48: =H44+H41 -> 568318.32 | I48: =I44+I41 -> 1250189.7 | J48: =J44+J41 -> 1632116.2 | K48: =K44+K41 -> 2408806.2 | L48: =L44+L41 -> 0 | M48: =M44+M41 -> 0 | N48: =N44+N41 -> 0 | ... P48: =P44+P41 -> 0 | Q48: =SUM(G48:P48) -> 6091203.1
E49: Cumulative Contribution | G49: =G48 -> 231772.64 | H49: =G49+H48 -> 800090.95 | I49: =H49+I48 -> 2050280.7 | J49: =I49+J48 -> 3682396.9 | K49: =J49+K48 -> 6091203.1 | L49: =K49+L48 -> 6091203.1 | M49: =L49+M48 -> 6091203.1 | N49: =M49+N48 -> 6091203.1 | O49: =N49+O48 -> 6091203.1 | P49: =O49+P48 -> 6091203.1 | Q49: =Q48 -> 6091203.1
E51: Cumulative NPV | G51: =G57 -> 206611.49 | H51: =H57 -> 676296.05 | I51: =I57 -> 1615582.1 | J51: =J57 -> 2730339.4 | K51: =K57 -> 4226018.5 | L51: =L57 -> 4226018.5 | M51: =M57 -> 4226018.5 | N51: =N57 -> 4226018.5 | ... P51: =P57 -> 4226018.5 | Q51: =P51 -> 4226018.5
E53: Per Transaction Yield | G53: =IFERROR(G41/G7,0) -> 0.23876425 | H53: =IFERROR(H41/H7,0) -> 0.3876985 | I53: =IFERROR(I41/I7,0) -> 0.48156618 | J53: =IFERROR(J41/J7,0) -> 0.42609025 | K53: =IFERROR(K41/K7,0) -> 0.42731914 | L53: =IFERROR(L41/L7,0) -> 0 | M53: =IFERROR(M41/M7,0) -> 0 | N53: =IFERROR(N41/N7,0) -> 0 | ... Q53: =IFERROR(Q41/Q7,0) -> 0.42016637
E54: NRY (on PV) | G54: =IFERROR(G41/G6*10000,0) -> 11.971887 | H54: =IFERROR(H41/H6*10000,0) -> 19.876046 | I54: =IFERROR(I41/I6*10000,0) -> 25.244547 | J54: =IFERROR(J41/J6*10000,0) -> 22.336401 | K54: =IFERROR(K41/K6*10000,0) -> 22.502213 | L54: =IFERROR(L41/L6*10000,0) -> 0 | M54: =IFERROR(M41/M6*10000,0) -> 0 | N54: =IFERROR(N41/N6*10000,0) -> 0 | ... Q54: =IFERROR(Q41/Q6*10000,0) -> 21.943592
E55: Cumulative NRY (on PV) | G55: =IFERROR(SUM($G$41:G41)/SUM($G$6:G6)*10000,"") -> 11.971887 | H55: =IFERROR(SUM($G$41:H41)/SUM($G$6:H6)*10000,"") -> 16.853852 | I55: =IFERROR(SUM($G$41:I41)/SUM($G$6:I6)*10000,"") -> 21.081762 | J55: =IFERROR(SUM($G$41:J41)/SUM($G$6:J6)*10000,"") -> 21.603414 | K55: =IFERROR(SUM($G$41:K41)/SUM($G$6:K6)*10000,"") -> 21.943592 | L55: =IFERROR(SUM($G$41:L41)/SUM($G$6:L6)*10000,"") -> 21.943592 | M55: =IFERROR(SUM($G$41:M41)/SUM($G$6:M6)*10000,"") -> 21.943592 | N55: =IFERROR(SUM($G$41:N41)/SUM($G$6:N6)*10000,"") -> 21.943592 | ... P55: =IFERROR(SUM($G$41:P41)/SUM($G$6:P6)*10000,"") -> 21.943592 | Q55: =P55 -> 21.943592 | T55: =SUM(G117:H117) -> -49423.444
E57: NPV (Cumulative) | G57: =G62 -> 206611.49 | H57: =H62 -> 676296.05 | I57: =I62 -> 1615582.1 | J57: =J62 -> 2730339.4 | K57: =K62 -> 4226018.5 | L57: =L62 -> 4226018.5 | M57: =M62 -> 4226018.5 | N57: =N62 -> 4226018.5 | ... Q57: =Q62 -> 4226018.5
G59: 1 | H59: 2 | I59: 3 | J59: 4 | K59: 5 | L59: 6 | M59: 7 | N59: 8 | O59: 9 | P59: 10
F60: 1 | G60: =(1+$E$61)^-G59 -> 0.90909091 | H60: =(1+$E$61)^-H59 -> 0.82644628 | I60: =(1+$E$61)^-I59 -> 0.7513148 | J60: =(1+$E$61)^-J59 -> 0.68301346 | K60: =(1+$E$61)^-K59 -> 0.62092132 | L60: =(1+$E$61)^-L59 -> 0.56447393 | M60: =(1+$E$61)^-M59 -> 0.51315812 | N60: =(1+$E$61)^-N59 -> 0.46650738 | ... P60: =(1+$E$61)^-P59 -> 0.38554329
E61: 0.1 | F61: =G34 -> -45000 | G61: =G60*SUM(G36:G39,G18,G44) -> 251611.49 | H61: =H60*SUM(H36:H39,H18,H44) -> 469684.56 | I61: =I60*SUM(I36:I39,I18,I44) -> 939286.03 | J61: =J60*SUM(J36:J39,J18,J44) -> 1114757.3 | K61: =K60*SUM(K36:K39,K18,K44) -> 1495679.1 | L61: =L60*SUM(L36:L39,L18,L44) -> 0 | M61: =M60*SUM(M36:M39,M18,M44) -> 0 | N61: =N60*SUM(N36:N39,N18,N44) -> 0 | ... P61: =P60*SUM(P36:P39,P18,P44) -> 0 | Q61: =SUM(F61:P61) -> 4226018.5
E62: NPV | F62: =F61 -> -45000 | G62: =F62+G61 -> 206611.49 | H62: =G62+H61 -> 676296.05 | I62: =H62+I61 -> 1615582.1 | J62: =I62+J61 -> 2730339.4 | K62: =J62+K61 -> 4226018.5 | L62: =K62+L61 -> 4226018.5 | M62: =L62+M61 -> 4226018.5 | N62: =M62+N61 -> 4226018.5 | ... P62: =O62+P61 -> 4226018.5 | Q62: =IFERROR(HLOOKUP($C$15,$G$59:$P$62,4,0),0) -> 4226018.5
E64: 0.53239437 | F64: Auth | G64: =G$66*$E64 -> 0.0013964704 | H64: =H$66*$E64 -> 0.0012883944 | I64: =I$66*$E64 -> 0.0012074704 | J64: =J$66*$E64 -> 0.0011419859 | K64: =K$66*$E64 -> 0.0010860845 | L64: =L$66*$E64 -> 0.0010360394 | M64: =M$66*$E64 -> 0.00099025352 | N64: =N$66*$E64 -> 0.00094819437 | ... P64: =P$66*$E64 -> 0.00094819437
E65: 0.46760563 | F65: C&S | G65: =G$66*$E65 -> 0.0012265296 | H65: =H$66*$E65 -> 0.0011316056 | I65: =I$66*$E65 -> 0.0010605296 | J65: =J$66*$E65 -> 0.0010030141 | K65: =K$66*$E65 -> 0.00095391549 | L65: =L$66*$E65 -> 0.00090996056 | M65: =M$66*$E65 -> 0.00086974648 | N65: =N$66*$E65 -> 0.00083280563 | ... P65: =P$66*$E65 -> 0.00083280563
F66: Total Variable Processing Costs | G66: 0.002623 | H66: 0.00242 | I66: 0.002268 | J66: 0.002145 | K66: 0.00204 | L66: 0.001946 | M66: 0.00186 | N66: 0.001781 | O66: 0.001781 | P66: 0.001781
F67: Core Fees | G67: =SUM(G19,G20,G22,G23,G25) -> 177397.93 | H67: =SUM(H19,H20,H22,H23,H25) -> 398139.06 | I67: =SUM(I19,I20,I22,I23,I25) -> 843112.2 | J67: =SUM(J19,J20,J22,J23,J25) -> 1190811.7 | K67: =SUM(K19,K20,K22,K23,K25) -> 1824158.6 | L67: =SUM(L19,L20,L22,L23,L25) -> 0 | M67: =SUM(M19,M20,M22,M23,M25) -> 0 | N67: =SUM(N19,N20,N22,N23,N25) -> 0 | ... P67: =SUM(P19,P20,P22,P23,P25) -> 0 | Q67: =SUM(G67:P67) -> 4433619.5
F68: Amortized Discount | G68: =-$G$2*G67 -> -5321.9379 | H68: =-$G$2*H67 -> -11944.172 | I68: =-$G$2*I67 -> -25293.366 | J68: =-$G$2*J67 -> -35724.35 | K68: =-$G$2*K67 -> -54724.759 | L68: =-$G$2*L67 -> 0 | M68: =-$G$2*M67 -> 0 | N68: =-$G$2*N67 -> 0 | ... P68: =-$G$2*P67 -> 0 | Q68: =SUM(G68:P68) -> -133008.59
E69: OCT only (destination) | F69: Net Issuing Yield (Please Update for Market) | G69: 0.5 | H69: =G69*0.9 -> 0.45 | I69: =H69*0.9 -> 0.405 | J69: =I69*0.9 -> 0.3645 | K69: =J69*0.9 -> 0.32805 | L69: =K69*0.9 -> 0.295245 | M69: =L69*0.9 -> 0.2657205 | N69: =M69*0.9 -> 0.23914845 | O69: =N69*0.9 -> 0.21523361 | P69: =O69*0.9 -> 0.19371024
E70: AFT Only (originator market) | F70: Net Issuing Yield (Please Update for Market) | G70: 0.5 | H70: =G70*0.9 -> 0.45 | I70: =H70*0.9 -> 0.405 | J70: =I70*0.9 -> 0.3645 | K70: =J70*0.9 -> 0.32805 | L70: =K70*0.9 -> 0.295245 | M70: =L70*0.9 -> 0.2657205 | N70: =M70*0.9 -> 0.23914845 | O70: =N70*0.9 -> 0.21523361 | P70: =O70*0.9 -> 0.19371024
F71: OCT PV (DOM, IntraEEA, Intra NonEEA) | G71: =SUM(Inputs!E21:E24,Inputs!E36:E39) -> 1.2768764e+08 | H71: =SUM(Inputs!F21:F24,Inputs!F36:F39) -> 1.8452664e+08 | I71: =SUM(Inputs!G21:G24,Inputs!G36:G39) -> 2.6675796e+08 | J71: =SUM(Inputs!H21:H24,Inputs!H36:H39) -> 3.7676894e+08 | K71: =SUM(Inputs!I21:I24,Inputs!I36:I39) -> 5.3623844e+08 | L71: =SUM(Inputs!J21:J24,Inputs!J36:J39) -> 0 | M71: =SUM(Inputs!K21:K24,Inputs!K36:K39) -> 0 | N71: =SUM(Inputs!L21:L24,Inputs!L36:L39) -> 0 | ... P71: =SUM(Inputs!N21:N24,Inputs!N36:N39) -> 0
F72: AFT PV (DOM, IntraEEA, Intra NonEEA) | G72: =SUM(Inputs!E51:E54,Inputs!E66:E68) -> 46523100 | H72: =SUM(Inputs!F51:F54,Inputs!F66:F68) -> 76839320 | I72: =SUM(Inputs!G51:G54,Inputs!G66:G68) -> 1.2919983e+08 | J72: =SUM(Inputs!H51:H54,Inputs!H66:H68) -> 1.8248184e+08 | K72: =SUM(Inputs!I51:I54,Inputs!I66:I68) -> 2.684764e+08 | L72: =SUM(Inputs!J51:J54,Inputs!J66:J68) -> 0 | M72: =SUM(Inputs!K51:K54,Inputs!K66:K68) -> 0 | N72: =SUM(Inputs!L51:L54,Inputs!L66:L68) -> 0 | ... P72: =SUM(Inputs!N51:N54,Inputs!N66:N68) -> 0
F73: Total NS Issuing Fees | G73: =(G69*G71/10000)+(G70*G72/10000) -> 8710.5371 | H73: =(H69*H71/10000)+(H70*H72/10000) -> 11761.468 | I73: =(I69*I71/10000)+(I70*I72/10000) -> 16036.29 | J73: =(J69*J71/10000)+(J70*J72/10000) -> 20384.691 | K73: =(K69*K71/10000)+(K70*K72/10000) -> 26398.67 | L73: =(L69*L71/10000)+(L70*L72/10000) -> 0 | M73: =(M69*M71/10000)+(M70*M72/10000) -> 0 | N73: =(N69*N71/10000)+(N70*N72/10000) -> 0 | ... P73: =(P69*P71/10000)+(P70*P72/10000) -> 0
F74: Assessing Deal Term Contribution | G74: =IF(G59<=$C$15,IF(SUM($G$48:G48)>0,1,0),0) -> 1 | H74: =IF(H59<=$C$15,IF(SUM($G$48:H48)>0,1,0),0) -> 1 | I74: =IF(I59<=$C$15,IF(SUM($G$48:I48)>0,1,0),0) -> 1 | J74: =IF(J59<=$C$15,IF(SUM($G$48:J48)>0,1,0),0) -> 1 | K74: =IF(K59<=$C$15,IF(SUM($G$48:K48)>0,1,0),0) -> 1 | L74: =IF(L59<=$C$15,IF(SUM($G$48:L48)>0,1,0),0) -> 0 | M74: =IF(M59<=$C$15,IF(SUM($G$48:M48)>0,1,0),0) -> 0 | N74: =IF(N59<=$C$15,IF(SUM($G$48:N48)>0,1,0),0) -> 0 | ... P74: =IF(P59<=$C$15,IF(SUM($G$48:P48)>0,1,0),0) -> 0 | Q74: =IF(SUM(G74:P74)<C15,0,1) -> 1 | S74: =IF(Q74=0,"Check - does not break even","OK") -> OK
E75: Breakeven Year based on Contribution (Cash flow) | G75: =IF(SUM($G$48:G48)>0,1,0) -> 1 | H75: =IF(SUM($G$75:G75)=1,0,IF(SUM($G$48:H48)>0,1,0)) -> 0 | I75: =IF(SUM($G$75:H75)=1,0,IF(SUM($G$48:I48)>0,1,0)) -> 0 | J75: =IF(SUM($G$75:I75)=1,0,IF(SUM($G$48:J48)>0,1,0)) -> 0 | K75: =IF(SUM($G$75:J75)=1,0,IF(SUM($G$48:K48)>0,1,0)) -> 0 | L75: =IF(SUM($G$75:K75)=1,0,IF(SUM($G$48:L48)>0,1,0)) -> 0 | M75: =IF(SUM($G$75:L75)=1,0,IF(SUM($G$48:M48)>0,1,0)) -> 0 | N75: =IF(SUM($G$75:M75)=1,0,IF(SUM($G$48:N48)>0,1,0)) -> 0 | O75: =IF(SUM($G$75:N75)=1,0,IF(SUM($G$48:O48)>0,1,0)) -> 0 | P75: =IF(SUM($G$75:O75)=1,0,IF(SUM($G$48:P48)>0,1,0)) -> 0 | Q75: =IF(SUM(G75:P75)>1,"Error",MATCH(1,G75:P75,0)) -> 1
N76: Check with finance to change tiers
N77: Option 2 Discount Table
G78: Core Revenue Split by Prod | H78: % Split | I78: %Split Over ride | N78: XB OCT Txns from | O78: XB OCT Txns to | P78: Discount on Core XB OCTFees
E79: OCT P2P DOM | G79: =SUM([1]Calcs!AN145:AW145) -> 102056.63 | H79: =IF(I79=0,G79/SUM($G$79:$G$87),I79) -> 0.023018806 | I79: 0 | N79: 0 | O79: 99999 | P79: 0
E80: OCT P2P Intra | G80: =SUM([1]Calcs!AN146:AW146) -> 0 | H80: =IF(I80=0,G80/SUM($G$79:$G$87),I80) -> 0 | I80: 0 | N80: =O79+1 -> 100000 | O80: 499999 | P80: 0.1
E81: OCT P2P Inter | G81: =SUM([1]Calcs!AN147:AW148) -> 3990765.3 | H81: =IF(I81=0,G81/SUM($G$79:$G$87),I81) -> 0.90011452 | I81: 0 | N81: =O80+1 -> 500000 | O81: 1499999 | P81: 0.2
E82: OCT FD DOM | G82: =SUM([1]Calcs!AN139:AW139) -> 0 | H82: =IF(I82=0,G82/SUM($G$79:$G$87),I82) -> 0 | I82: 0 | N82: =O81+1 -> 1500000 | O82: 2999999 | P82: 0.25
E83: OCT FD Intra | G83: =SUM([1]Calcs!AN140:AW140) -> 0 | H83: =IF(I83=0,G83/SUM($G$79:$G$87),I83) -> 0 | I83: 0 | N83: =O82+1 -> 3000000 | O83: Uncapped | P83: 0.3
E84: OCT FD Inter | G84: =SUM([1]Calcs!AN141:AW142) -> 0 | H84: =IF(I84=0,G84/SUM($G$79:$G$87),I84) -> 0 | I84: 0
E85: AFT DOM | G85: =SUM([1]Calcs!AN133:AW133) -> 178560.28 | H85: =IF(I85=0,G85/SUM($G$79:$G$87),I85) -> 0.040274156 | I85: 0
E86: AFT Intra | G86: =SUM([1]Calcs!AN134:AW134) -> 0 | H86: =IF(I86=0,G86/SUM($G$79:$G$87),I86) -> 0 | I86: 0 | N86: Option 3 Discount Table, use with XB table above
E87: AFT Inter | G87: =SUM([1]Calcs!AN135:AW136) -> 162237.29 | H87: =IF(I87=0,G87/SUM($G$79:$G$87),I87) -> 0.036592516 | I87: 0 | N87: DOM/Intra OCT From | O87: DOM/Intra OCT To | P87: Discount on Total Core Fees
N88: 0 | O88: 500000 | P88: 0
N89: =O88+1 -> 500001 | O89: 1500000 | P89: 0.1
N90: =O89+1 -> 1500001 | O90: 3000000 | P90: 0.125
N91: =O90+1 -> 3000001 | O91: 5000000 | P91: 0.15
N92: =O91+1 -> 5000001 | O92: 50000000 | P92: 0.2
E98: BELOW INCENTIVE CALC
E99: XB OCT Txn | G99: =Inputs!E32+Inputs!E47+Inputs!E31+Inputs!E46 -> 165585.29 | H99: =Inputs!F32+Inputs!F47+Inputs!F31+Inputs!F46 -> 400158.03 | I99: =Inputs!G32+Inputs!G47+Inputs!G31+Inputs!G46 -> 882021.82 | J99: =Inputs!H32+Inputs!H47+Inputs!H31+Inputs!H46 -> 1245767.6 | K99: =Inputs!I32+Inputs!I47+Inputs!I31+Inputs!I46 -> 1919772.5 | L99: =Inputs!J32+Inputs!J47+Inputs!J31+Inputs!J46 -> 0 | M99: =Inputs!K32+Inputs!K47+Inputs!K31+Inputs!K46 -> 0 | N99: =Inputs!L32+Inputs!L47+Inputs!L31+Inputs!L46 -> 0 | ... P99: =Inputs!N32+Inputs!N47+Inputs!N31+Inputs!N46 -> 0
E100: XB OCT PV | G100: =Inputs!E24+Inputs!E25+Inputs!E39+Inputs!E40 -> 26626486 | H100: =Inputs!F24+Inputs!F25+Inputs!F39+Inputs!F40 -> 63225725 | I100: =Inputs!G24+Inputs!G25+Inputs!G39+Inputs!G40 -> 1.3810561e+08 | J100: =Inputs!H24+Inputs!H25+Inputs!H39+Inputs!H40 -> 1.9506037e+08 | K100: =Inputs!I24+Inputs!I25+Inputs!I39+Inputs!I40 -> 3.0019697e+08 | L100: =Inputs!J24+Inputs!J25+Inputs!J39+Inputs!J40 -> 0 | M100: =Inputs!K24+Inputs!K25+Inputs!K39+Inputs!K40 -> 0 | N100: =Inputs!L24+Inputs!L25+Inputs!L39+Inputs!L40 -> 0 | ... P100: =Inputs!N24+Inputs!N25+Inputs!N39+Inputs!N40 -> 0
E101: XB OCT Fee discount | G101: =VLOOKUP(G99,$N$79:$P$84,3,1) -> 0.1 | H101: =VLOOKUP(H99,$N$79:$P$84,3,1) -> 0.1 | I101: =VLOOKUP(I99,$N$79:$P$84,3,1) -> 0.2 | J101: =VLOOKUP(J99,$N$79:$P$84,3,1) -> 0.2 | K101: =VLOOKUP(K99,$N$79:$P$84,3,1) -> 0.25 | L101: =VLOOKUP(L99,$N$79:$P$84,3,1) -> 0 | M101: =VLOOKUP(M99,$N$79:$P$84,3,1) -> 0 | N101: =VLOOKUP(N99,$N$79:$P$84,3,1) -> 0 | ... P101: =VLOOKUP(P99,$N$79:$P$84,3,1) -> 0
E102: Incentive on XB OCT | G102: =-G101*SUM([1]Calcs!AN141:AN142,[1]Calcs!AN147:AN148) -> -14602.011 | H102: =-H101*SUM([1]Calcs!AO141:AO142,[1]Calcs!AO147:AO148) -> -34821.433 | I102: =-I101*SUM([1]Calcs!AP141:AP142,[1]Calcs!AP147:AP148) -> -152461.02 | J102: =-J101*SUM([1]Calcs!AQ141:AQ142,[1]Calcs!AQ147:AQ148) -> -215335.94 | K102: =-K101*SUM([1]Calcs!AR141:AR142,[1]Calcs!AR147:AR148) -> -414386.51 | L102: =-L101*SUM([1]Calcs!AS141:AS142,[1]Calcs!AS147:AS148) -> 0 | M102: =-M101*SUM([1]Calcs!AT141:AT142,[1]Calcs!AT147:AT148) -> 0 | N102: =-N101*SUM([1]Calcs!AU141:AU142,[1]Calcs!AU147:AU148) -> 0 | ... P102: =-P101*SUM([1]Calcs!AW141:AW142,[1]Calcs!AW147:AW148) -> 0
E104: DOM/Intra OCT Txns | G104: =SUM(Inputs!E28:E30,Inputs!E43:E45) -> 589414.71 | H104: =SUM(Inputs!F28:F30,Inputs!F43:F45) -> 846828.67 | I104: =SUM(Inputs!G28:G30,Inputs!G43:G45) -> 1214697.2 | J104: =SUM(Inputs!H28:H30,Inputs!H43:H45) -> 1715638.4 | K104: =SUM(Inputs!I28:I30,Inputs!I43:I45) -> 2437196.1 | L104: =SUM(Inputs!J28:J30,Inputs!J43:J45) -> 0 | M104: =SUM(Inputs!K28:K30,Inputs!K43:K45) -> 0 | N104: =SUM(Inputs!L28:L30,Inputs!L43:L45) -> 0 | ... P104: =SUM(Inputs!N28:N30,Inputs!N43:N45) -> 0
E105: DOM/Intra OCT Fee discount | G105: =VLOOKUP(G104,$N$88:$P$92,3,1) -> 0.1 | H105: =VLOOKUP(H104,$N$88:$P$92,3,1) -> 0.1 | I105: =VLOOKUP(I104,$N$88:$P$92,3,1) -> 0.1 | J105: =VLOOKUP(J104,$N$88:$P$92,3,1) -> 0.125 | K105: =VLOOKUP(K104,$N$88:$P$92,3,1) -> 0.125 | L105: =VLOOKUP(L104,$N$88:$P$92,3,1) -> 0 | M105: =VLOOKUP(M104,$N$88:$P$92,3,1) -> 0 | N105: =VLOOKUP(N104,$N$88:$P$92,3,1) -> 0 | ... P105: =VLOOKUP(P104,$N$88:$P$92,3,1) -> 0
E106: Incentive on DOM/Intra OCT | G106: =-G105*SUM([1]Calcs!AN139:AN140,[1]Calcs!AN145:AN146) -> -884.12207 | H106: =-H105*SUM([1]Calcs!AO139:AO140,[1]Calcs!AO145:AO146) -> -1270.243 | I106: =-I105*SUM([1]Calcs!AP139:AP140,[1]Calcs!AP145:AP146) -> -1822.0459 | J106: =-J105*SUM([1]Calcs!AQ139:AQ140,[1]Calcs!AQ145:AQ146) -> -3216.822 | K106: =-K105*SUM([1]Calcs!AR139:AR140,[1]Calcs!AR145:AR146) -> -4569.7427 | L106: =-L105*SUM([1]Calcs!AS139:AS140,[1]Calcs!AS145:AS146) -> 0 | M106: =-M105*SUM([1]Calcs!AT139:AT140,[1]Calcs!AT145:AT146) -> 0 | N106: =-N105*SUM([1]Calcs!AU139:AU140,[1]Calcs!AU145:AU146) -> 0 | ... P106: =-P105*SUM([1]Calcs!AW139:AW140,[1]Calcs!AW145:AW146) -> 0
E109: Select Incentive Option
E110: Option 1 (Input Flat Discount %, excludes AFT) | G110: =-SUM([1]Calcs!AN143,[1]Calcs!AN149)*'P&L'!$G$2 -> -4645.8399 | H110: =-SUM([1]Calcs!AO143,[1]Calcs!AO149)*'P&L'!$G$2 -> -10827.503 | I110: =-SUM([1]Calcs!AP143,[1]Calcs!AP149)*'P&L'!$G$2 -> -23415.767 | J110: =-SUM([1]Calcs!AQ143,[1]Calcs!AQ149)*'P&L'!$G$2 -> -33072.429 | K110: =-SUM([1]Calcs!AR143,[1]Calcs!AR149)*'P&L'!$G$2 -> -50823.12 | L110: =-SUM([1]Calcs!AS143,[1]Calcs!AS149)*'P&L'!$G$2 -> 0 | M110: =-SUM([1]Calcs!AT143,[1]Calcs!AT149)*'P&L'!$G$2 -> 0 | N110: =-SUM([1]Calcs!AU143,[1]Calcs!AU149)*'P&L'!$G$2 -> 0 | ... P110: =-SUM([1]Calcs!AW143,[1]Calcs!AW149)*'P&L'!$G$2 -> 0
E111: Option 2 (Only XB OCTs, tiered discount) | G111: =G102 -> -14602.011 | H111: =H102 -> -34821.433 | I111: =I102 -> -152461.02 | J111: =J102 -> -215335.94 | K111: =K102 -> -414386.51 | L111: =L102 -> 0 | M111: =M102 -> 0 | N111: =N102 -> 0 | ... P111: =P102 -> 0
E112: Option 3 (Tiered DOM/Intra OCT, Tiered XB OCT) | G112: =G106+G102 -> -15486.133 | H112: =H106+H102 -> -36091.676 | I112: =I106+I102 -> -154283.07 | J112: =J106+J102 -> -218552.77 | K112: =K106+K102 -> -418956.25 | L112: =L106+L102 -> 0 | M112: =M106+M102 -> 0 | N112: =N106+N102 -> 0 | ... P112: =P106+P102 -> 0
G116: 3 | H116: 4 | I116: 5 | J116: 6 | K116: 7 | L116: 8 | M116: 9 | N116: 10 | O116: 11 | P116: 12
E117: Final Discount as per Option | G117: =VLOOKUP($F$2,$E$110:$P$112,G116,0) -> -14602.011 | H117: =VLOOKUP($F$2,$E$110:$P$112,H116,0) -> -34821.433 | I117: =VLOOKUP($F$2,$E$110:$P$112,I116,0) -> -152461.02 | J117: =VLOOKUP($F$2,$E$110:$P$112,J116,0) -> -215335.94 | K117: =VLOOKUP($F$2,$E$110:$P$112,K116,0) -> -414386.51 | L117: =VLOOKUP($F$2,$E$110:$P$112,L116,0) -> 0 | M117: =VLOOKUP($F$2,$E$110:$P$112,M116,0) -> 0 | N117: =VLOOKUP($F$2,$E$110:$P$112,N116,0) -> 0 | ... P117: =VLOOKUP($F$2,$E$110:$P$112,P116,0) -> 0
E118: DOM/Intra | G118: =G117-G119 -> 0 | H118: =H117-H119 -> 0 | I118: =I117-I119 -> 0 | J118: =J117-J119 -> 0 | K118: =K117-K119 -> 0 | L118: =L117-L119 -> 0 | M118: =M117-M119 -> 0 | N118: =N117-N119 -> 0 | ... P118: =P117-P119 -> 0
E119: Inter | G119: =IF($F$2=$E$110,-SUM([1]Calcs!AN141:AN142,[1]Calcs!AN147:AN148)*$G$2,IF($F$2=$E$111,G102,G102)) -> -14602.011 | H119: =IF($F$2=$E$110,-SUM([1]Calcs!AO141:AO142,[1]Calcs!AO147:AO148)*$G$2,IF($F$2=$E$111,H102,H102)) -> -34821.433 | I119: =IF($F$2=$E$110,-SUM([1]Calcs!AP141:AP142,[1]Calcs!AP147:AP148)*$G$2,IF($F$2=$E$111,I102,I102)) -> -152461.02 | J119: =IF($F$2=$E$110,-SUM([1]Calcs!AQ141:AQ142,[1]Calcs!AQ147:AQ148)*$G$2,IF($F$2=$E$111,J102,J102)) -> -215335.94 | K119: =IF($F$2=$E$110,-SUM([1]Calcs!AR141:AR142,[1]Calcs!AR147:AR148)*$G$2,IF($F$2=$E$111,K102,K102)) -> -414386.51 | L119: =IF($F$2=$E$110,-SUM([1]Calcs!AS141:AS142,[1]Calcs!AS147:AS148)*$G$2,IF($F$2=$E$111,L102,L102)) -> 0 | M119: =IF($F$2=$E$110,-SUM([1]Calcs!AT141:AT142,[1]Calcs!AT147:AT148)*$G$2,IF($F$2=$E$111,M102,M102)) -> 0 | N119: =IF($F$2=$E$110,-SUM([1]Calcs!AU141:AU142,[1]Calcs!AU147:AU148)*$G$2,IF($F$2=$E$111,N102,N102)) -> 0 | ... P119: =IF($F$2=$E$110,-SUM([1]Calcs!AW141:AW142,[1]Calcs!AW147:AW148)*$G$2,IF($F$2=$E$111,P102,P102)) -> 0
E121: Incentive split by jurisdiction
E122: Dom only | G122: =IF($F$2=$E$110,SUM([1]Calcs!AN139,[1]Calcs!AN145)*$G$2,IF($F$2=$E$112,SUM([1]Calcs!AN139,[1]Calcs!AN145)*G105,0)) -> 0 | H122: =IF($F$2=$E$110,SUM([1]Calcs!AO139,[1]Calcs!AO145)*$G$2,IF($F$2=$E$112,SUM([1]Calcs!AO139,[1]Calcs!AO145)*H105,0)) -> 0 | I122: =IF($F$2=$E$110,SUM([1]Calcs!AP139,[1]Calcs!AP145)*$G$2,IF($F$2=$E$112,SUM([1]Calcs!AP139,[1]Calcs!AP145)*I105,0)) -> 0 | J122: =IF($F$2=$E$110,SUM([1]Calcs!AQ139,[1]Calcs!AQ145)*$G$2,IF($F$2=$E$112,SUM([1]Calcs!AQ139,[1]Calcs!AQ145)*J105,0)) -> 0 | K122: =IF($F$2=$E$110,SUM([1]Calcs!AR139,[1]Calcs!AR145)*$G$2,IF($F$2=$E$112,SUM([1]Calcs!AR139,[1]Calcs!AR145)*K105,0)) -> 0 | L122: =IF($F$2=$E$110,SUM([1]Calcs!AS139,[1]Calcs!AS145)*$G$2,IF($F$2=$E$112,SUM([1]Calcs!AS139,[1]Calcs!AS145)*L105,0)) -> 0 | M122: =IF($F$2=$E$110,SUM([1]Calcs!AT139,[1]Calcs!AT145)*$G$2,IF($F$2=$E$112,SUM([1]Calcs!AT139,[1]Calcs!AT145)*M105,0)) -> 0 | N122: =IF($F$2=$E$110,SUM([1]Calcs!AU139,[1]Calcs!AU145)*$G$2,IF($F$2=$E$112,SUM([1]Calcs!AU139,[1]Calcs!AU145)*N105,0)) -> 0 | ... P122: =IF($F$2=$E$110,SUM([1]Calcs!AW139,[1]Calcs!AW145)*$G$2,IF($F$2=$E$112,SUM([1]Calcs!AW139,[1]Calcs!AW145)*P105,0)) -> 0
...
