Workbook
Name AccrualsTemplate: "Button 12"
Name AcquirerAFTFees: [1]Schedules!#REF!
Name AcquirerFeeOptions: [1]Automation!#REF!
Name AcquirerOCTFees: [1]Schedules!#REF!
Name Activity: "Button 59"
Name AddressNoticeAddress: [1]Automation!#REF!
Name AFT: '[1]Dropdown Logic'!$AM$5:$AM$13
Name ApprovalRoute: '[1]MI Database Template'!$P$9:$P$14
Name dcDaysInWeek: 7
Name dcDaysInYear: 365
Name dcMthsInQtr: 3
Name dcMthsInYear: 12
Name dcQtrsInYear: 4
Name dcWeeksInYear: 52
Name DetailedOpenPurchaseOrderListing: "Button 11"
Name DetailedTransactionListings: "Button 9"
Name dMthsInYear: 12
Name FastTrack: [1]Automation!#REF!
Name GraphCumulativeSpend: "Button 5"
Name GraphPhasedSpend: "Button 3"
Name GraphYTDSpendByCategory: "Button 6"
Name HeadlineCategory: "Button 2"
Name Incentive_Options: 'P&L'!$E$108:$E$113
Name Last_Row: #N/A
Name Model: '[2]1b) Forecast Inputs '!$C$4
Name NoticeAddress: [1]Automation!#REF!
Name Number_of_Payments: #N/A
Name OCT: '[1]Dropdown Logic'!$AN$5:$AN$21
Name Payment_Date: #N/A
Name Phased: "Button 61"
Name PhasedReportsActByAccount: "Button 8"
Name Print_Area_Reset: #N/A
Name rtrtrr: #N/A
Name ss: #N/A
Name StrategicPricingPresent: [1]Automation!#REF!
Name TableName: "Dummy"
Name TM1REBUILDOPTION: 0
Name Values_Entered: #N/A
Name VersNo: 0.22
Name YTDVarianceKey: "Object 4"

Sheet Intro
A1: Model Version | C1: ='[1]Change Control'!C11 -> vJun24 eff 01/07/2024
B2: Please fill all cells in Yellow | D2: Opportunity ID (OPP-000XXXXXX) | E2: OPP-001060809 | F2: Deal Owner (AE) | G2: Emma Attali | H2: Scenario Name | I2: MLS | K2: Deal Checks Please ensure all checks are green | N2: Include Reason if exception
B3: Client Name | C3: Trading212 CKO LA | D3: Primary Market | E3: UK | F3: Cluster | G3: =IFERROR(VLOOKUP($E$3,'[1]Deals Database'!$B$12:$C$60,2,0),"") -> UK + Eire | H3: CI Ref (Finance to complete) | I3: FY25_421
B4: Executive Summary: (Background - Overview of Client & Business Opportunity - What has triggered this request?)
B5: Checkout is bringing to Visa a list of 15 new merchants representing an annual incremental PV of €55BN for Visa Checkout has provided information on volumes from existing merchants that Visa does not capture today, representing an annual incremental PV of €29BN for Visa. | K5: Within Fast Track | L5: =IF(COUNTIF($L$7:$L$15,"No")>0,"No","Yes") -> Yes
B6: Alignment with VE Corporate goals: (How does this deal support VE’s corporate goals? )
B7: Increase PV volumes on card rails - Capture incremental PV and net revenues for Visa. | K7: Upfront <$250K | L7: =IF(-'P&L'!$G$34*Inputs!$O$1<=250000,"Yes","No") -> Yes
B8: Win / Retain Strategy (What is the sales strategy? - Idea of what the amount and structure of incentives & Client request?) | C8: 0 | D8: 0 | E8: 0 | F8: 0 | G8: 0 | H8: 0 | I8: 0
B9: Winning new business with CKO and Liquid Assets merchants Retaining key liquid assets merchants such as Interactive Investors whose volumes are declining (-46% from 2025 to 2024) | K9: Incentive Earn-Through and Contribution B/E by Year 3 | L9: =IF(OR(SUM('P&L'!G37:I37)<=0,SUM('P&L'!G74:I74)<1),"Yes","No") -> Yes
B10: Key Benefits (What are the key reasons for approval?) | C10: 0 | D10: 0 | E10: 0 | F10: 0 | G10: 0 | H10: 0 | I10: 0
B11: Incremental PV / Net revenues for Visa and issuers (on new merchants to card rails) Supporting CKO to retain volumes on card rails with key merchants moving away from card rails because of AFT Pricing uncapped in that sector | K11: Discount on Core Fees <=35% | L11: =IF(-'P&L'!C29<=35%,"Yes","No") -> Yes
B12: Key Commercial Concerns (What are the key concerns about this opportunity?)
K13: Total Incenitves excl. IRR VAT < $10M | L13: =IF(-('P&L'!Q33-'P&L'!Q38)<10000000/Inputs!O1,"Yes","No") -> Yes | N13: Provide exception why this deal should be within Fast Track
B14: What other factors should be considered? (Concerns about the client?) | C14: 0 | D14: 0 | E14: 0 | F14: 0 | G14: 0 | H14: 0 | I14: 0
K15: Upfront < 25% of Total Incentives | L15: =IF('P&L'!Q34>='P&L'!Q33*0.25,"Yes","No") -> Yes
B17: Please complete the following for Contract Management: | F17: Please complete the following Client information:
B18: Deal Term | D18: 2 | E18: =IF(D18="","Mandatory","") | F18: Client Full Name
B19: Any existing VD portfolio under contract? | D19: Yes | F19: Client Address
B20: If existing, when does the contract end? | D20: mm/yyyy | F20: Client Notice Address
B21: Start Date for the new deal (qtr beginning) | D21: 45931 | E21: =IF(D21="","Mandatory","") | F21: CW Number
B22: End Date for the new deal (qtr ending) | D22: =IFERROR(EOMONTH(D21-1,'P&L'!C15*12),"") -> 46660 | F22: FY Number | H22: =I3 -> FY25_421
B23: Break clause year (if any) | D23: 0 | F23: BID Identifier
B24: Microsoft Dynamics Ref (OPP-000XXXXXX) | D24: =E2 -> OPP-001060809
B25: Market Name (or Pan EU)? | D25: =Intro!E3 -> UK
B28: Sharepoint folder link for model and VDDR deck: | E28: https://visainc.sharepoint.com/:f:/r/sites/VDWPricingTemplateGroup/Shared%20Documents/AE%20Intake%20Form%20(VDC)?csf=1&web=1&e=shDlBz
B29: Link for AFT Money Load Program | E29: https://visa.highspot.com/items/64b7ed48d004140237384d7a
B30: Link for OCT Strategic Alliance Fee Program | E30: https://visa.highspot.com/items/64b7ed7e2b4f9c04ea94b456

Sheet P&L
F2: Option 1 (Input Flat Discount %, excludes AFT) | G2: 0 | H2: Option 1: Flat % discount on all core OCT fees (AFTs excluded), Max 35%. For small deals cap at 25% | J2: Option 2: Tiered XB Discount on XB OCTs only (refer to tiering Table) - standard tier table | L2: Option 3: Tiered % Discount on All OCTs, tiering by DOM/Intra and XB | N2: Enterprie Adj. AANR | O2: =(Q40+Q46)/Intro!D18 -> 462077 | P2: =O2*Inputs!O1 -> 514522.74 | Q2: EU VD Only Adj. AANR | R2: =SUM(Q19:Q25,Q33,Q46)/Intro!D18 -> 346885 | S2: =R2*Inputs!O1 -> 386256.45
F3: OCT Txn % | G3: =IFERROR(1-G4,"") -> 0 | H3: =IFERROR(1-H4,"") -> 0 | I3: =IFERROR(1-I4,"") | J3: =IFERROR(1-J4,"") | K3: =IFERROR(1-K4,"") | L3: =IFERROR(1-L4,"") | M3: =IFERROR(1-M4,"") | N3: =IFERROR(1-N4,"") | ... P3: =IFERROR(1-P4,"")
C4: =IFERROR(IF(AND(Intro!D22<>"", Intro!D21<>"", C15<>""), IF(ABS(DATEDIF(Intro!D21,Intro!D22,"D") - C15*365.25) > 5, "DATE ERROR",""),""),"Check Start/End Qtr") | F4: AFT Txn % | G4: =IFERROR(Inputs!E52/Inputs!E65,"") -> 1 | H4: =IFERROR(Inputs!F52/Inputs!F65,"") -> 1 | I4: =IFERROR(Inputs!G52/Inputs!G65,"") | J4: =IFERROR(Inputs!H52/Inputs!H65,"") | K4: =IFERROR(Inputs!I52/Inputs!I65,"") | L4: =IFERROR(Inputs!J52/Inputs!J65,"") | M4: =IFERROR(Inputs!K52/Inputs!K65,"") | N4: =IFERROR(Inputs!L52/Inputs!L65,"") | ... Q4: =IFERROR(Inputs!O52/Inputs!O65,"") -> 1
F5: Total | G5: 1 | H5: 2 | I5: 3 | J5: 4 | K5: 5 | L5: 6 | M5: 7 | N5: 8 | O5: 9 | P5: 10 | Q5: Total
F6: PV - Total EUROS | G6: =Inputs!E59 -> 1047200000 | H6: =Inputs!F59 -> 1047200000 | I6: =Inputs!G59 -> 0 | J6: =Inputs!H59 -> 0 | K6: =Inputs!I59 -> 0 | L6: =Inputs!J59 -> 0 | M6: =Inputs!K59 -> 0 | N6: =Inputs!L59 -> 0 | ... P6: =Inputs!N59 -> 0 | Q6: =SUM(G6:P6) -> 2094400000 | S6: =Q6=Q9+Q12+Q15 -> TRUE
F7: Transactions - Total | G7: =Inputs!E65 -> 6545000 | H7: =Inputs!F65 -> 6545000 | I7: =Inputs!G65 -> 0 | J7: =Inputs!H65 -> 0 | K7: =Inputs!I65 -> 0 | L7: =Inputs!J65 -> 0 | M7: =Inputs!K65 -> 0 | N7: =Inputs!L65 -> 0 | ... P7: =Inputs!N65 -> 0 | Q7: =SUM(G7:P7) -> 13090000 | S7: =Q7=Q10+Q13+Q16 -> TRUE
E9: PV and Volumes | F9: PV - EU Dom | G9: =Inputs!E60 -> 1047200000 | H9: =Inputs!F60 -> 1047200000 | I9: =Inputs!G60 -> 0 | J9: =Inputs!H60 -> 0 | K9: =Inputs!I60 -> 0 | L9: =Inputs!J60 -> 0 | M9: =Inputs!K60 -> 0 | N9: =Inputs!L60 -> 0 | ... P9: =Inputs!N60 -> 0 | Q9: =SUM(G9:P9) -> 2094400000 | S9: =Q9=Inputs!O60 -> TRUE
F10: Transactions - EU Dom | G10: =Inputs!E66 -> 6545000 | H10: =Inputs!F66 -> 6545000 | I10: =Inputs!G66 -> 0 | J10: =Inputs!H66 -> 0 | K10: =Inputs!I66 -> 0 | L10: =Inputs!J66 -> 0 | M10: =Inputs!K66 -> 0 | N10: =Inputs!L66 -> 0 | ... P10: =Inputs!N66 -> 0 | Q10: =SUM(G10:P10) -> 13090000 | S10: =Q10=Inputs!O66 -> TRUE
F12: PV - EU Intra (EEA + NON-EEA) | G12: =Inputs!E61 -> 0 | H12: =Inputs!F61 -> 0 | I12: =Inputs!G61 -> 0 | J12: =Inputs!H61 -> 0 | K12: =Inputs!I61 -> 0 | L12: =Inputs!J61 -> 0 | M12: =Inputs!K61 -> 0 | N12: =Inputs!L61 -> 0 | ... P12: =Inputs!N61 -> 0 | Q12: =SUM(G12:P12) -> 0 | S12: =Q12=Inputs!O61+Inputs!O62 -> TRUE
F13: Transactions - EU Intra | G13: =Inputs!E67+Inputs!E68 -> 0 | H13: =Inputs!F67+Inputs!F68 -> 0 | I13: =Inputs!G67+Inputs!G68 -> 0 | J13: =Inputs!H67+Inputs!H68 -> 0 | K13: =Inputs!I67+Inputs!I68 -> 0 | L13: =Inputs!J67+Inputs!J68 -> 0 | M13: =Inputs!K67+Inputs!K68 -> 0 | N13: =Inputs!L67+Inputs!L68 -> 0 | ... P13: =Inputs!N67+Inputs!N68 -> 0 | Q13: =SUM(G13:P13) -> 0 | S13: =Q13=Inputs!O67+Inputs!O68 -> TRUE
B14: Deal KPIs (EUROS)
B15: Term of Contract (years) | C15: =Inputs!I3 -> 2 | F15: PV - XB | G15: =Inputs!E63+Inputs!E62 -> 0 | H15: =Inputs!F63+Inputs!F62 -> 0 | I15: =Inputs!G63+Inputs!G62 -> 0 | J15: =Inputs!H63+Inputs!H62 -> 0 | K15: =Inputs!I63+Inputs!I62 -> 0 | L15: =Inputs!J63+Inputs!J62 -> 0 | M15: =Inputs!K63+Inputs!K62 -> 0 | N15: =Inputs!L63+Inputs!L62 -> 0 | ... P15: =Inputs!N63+Inputs!N62 -> 0 | Q15: =SUM(G15:P15) -> 0 | S15: =Q15=Inputs!O63 -> TRUE
B16: Total Transactions | C16: =Inputs!O65 -> 13090000 | F16: Transactions - XB | G16: =Inputs!E69+Inputs!E68 -> 0 | H16: =Inputs!F69+Inputs!F68 -> 0 | I16: =Inputs!G69+Inputs!G68 -> 0 | J16: =Inputs!H69+Inputs!H68 -> 0 | K16: =Inputs!I69+Inputs!I68 -> 0 | L16: =Inputs!J69+Inputs!J68 -> 0 | M16: =Inputs!K69+Inputs!K68 -> 0 | N16: =Inputs!L69+Inputs!L68 -> 0 | ... P16: =Inputs!N69+Inputs!N68 -> 0 | Q16: =SUM(G16:P16) -> 0 | S16: =Q16=SUM(Inputs!O68:O69) -> TRUE
B17: Average Annualised Tranactions | C17: =IFERROR(C16/C15,0) -> 6545000
B18: DOM Txn% | C18: =IFERROR(Inputs!P66,"check") -> 1 | E18: Fees/revenue | F18: Gross Revenue (OCT+AFT) | G18: =SUM(G19:G32) -> 464695 | H18: =SUM(H19:H32) -> 459459 | I18: =SUM(I19:I32) -> 0 | J18: =SUM(J19:J32) -> 0 | K18: =SUM(K19:K32) -> 0 | L18: =SUM(L19:L32) -> 0 | M18: =SUM(M19:M32) -> 0 | N18: =SUM(N19:N32) -> 0 | ... P18: =SUM(P19:P32) -> 0 | Q18: =SUM(G18:P18) -> 924154
B19: INTRA EEA Txn% | C19: =IFERROR(Inputs!P67,"check") -> 0 | F19: Acq Processing Rev - EU Dom | G19: =[1]Calcs!AY68 -> 53669 | H19: =[1]Calcs!AZ68 -> 53669 | I19: =[1]Calcs!BA68 -> 0 | J19: =[1]Calcs!BB68 -> 0 | K19: =[1]Calcs!BC68 -> 0 | L19: =[1]Calcs!BD68 -> 0 | M19: =[1]Calcs!BE68 -> 0 | N19: =[1]Calcs!BF68 -> 0 | ... P19: =[1]Calcs!BH68 -> 0 | Q19: =SUM(G19:P19) -> 107338
B20: INTRA Non-EEA Txn% | C20: =IFERROR(Inputs!P68,"check") -> 0 | F20: Acq Scheme Rev - EU Dom | G20: =[1]Calcs!AN68 -> 293216 | H20: =[1]Calcs!AO68 -> 293216 | I20: =[1]Calcs!AP68 -> 0 | J20: =[1]Calcs!AQ68 -> 0 | K20: =[1]Calcs!AR68 -> 0 | L20: =[1]Calcs!AS68 -> 0 | M20: =[1]Calcs!AT68 -> 0 | N20: =[1]Calcs!AU68 -> 0 | ... P20: =[1]Calcs!AW68 -> 0 | Q20: =SUM(G20:P20) -> 586432
B21: Inter Txn% | C21: =IFERROR(Inputs!P69,"check") -> 0
B22: Total Core Acquiring Fees | C22: =SUM(G19:P25) -> 693770 | F22: Acq Processing Rev - EU Intra | G22: =[1]Calcs!AY69 -> 0 | H22: =[1]Calcs!AZ69 -> 0 | I22: =[1]Calcs!BA69 -> 0 | J22: =[1]Calcs!BB69 -> 0 | K22: =[1]Calcs!BC69 -> 0 | L22: =[1]Calcs!BD69 -> 0 | M22: =[1]Calcs!BE69 -> 0 | N22: =[1]Calcs!BF69 -> 0 | ... P22: =[1]Calcs!BH69 -> 0 | Q22: =SUM(G22:P22) -> 0
B23: Total Gross Revenue | C23: =Q18 -> 924154 | F23: Acq Scheme Rev - EU Intra | G23: =[1]Calcs!AN69 -> 0 | H23: =[1]Calcs!AO69 -> 0 | I23: =[1]Calcs!AP69 -> 0 | J23: =[1]Calcs!AQ69 -> 0 | K23: =[1]Calcs!AR69 -> 0 | L23: =[1]Calcs!AS69 -> 0 | M23: =[1]Calcs!AT69 -> 0 | N23: =[1]Calcs!AU69 -> 0 | ... P23: =[1]Calcs!AW69 -> 0 | Q23: =SUM(G23:P23) -> 0
B24: Total Incentives incl IRR VAT | C24: =Q33 -> 0
B25: Total Net Revenue | C25: =IFERROR(Q40,0) -> 924154 | F25: Acquirer Rev - XB | G25: =SUM([1]Calcs!AN70:AN71,[1]Calcs!AY70:AY71) -> 0 | H25: =SUM([1]Calcs!AO70:AO71,[1]Calcs!AZ70:AZ71) -> 0 | I25: =SUM([1]Calcs!AP70:AP71,[1]Calcs!BA70:BA71) -> 0 | J25: =SUM([1]Calcs!AQ70:AQ71,[1]Calcs!BB70:BB71) -> 0 | K25: =SUM([1]Calcs!AR70:AR71,[1]Calcs!BC70:BC71) -> 0 | L25: =SUM([1]Calcs!AS70:AS71,[1]Calcs!BD70:BD71) -> 0 | M25: =SUM([1]Calcs!AT70:AT71,[1]Calcs!BE70:BE71) -> 0 | N25: =SUM([1]Calcs!AU70:AU71,[1]Calcs!BF70:BF71) -> 0 | ... P25: =SUM([1]Calcs!AW70:AW71,[1]Calcs!BH70:BH71) -> 0 | Q25: =SUM(G25:P25) -> 0 | S25: =SUM(Q20:Q25) -> 586432
B26: AANR | C26: =IFERROR(C25/C15,0) -> 462077 | F26: Issuer Rev (All Volumes) | G26: =G72 -> 52360 | H26: =H72 -> 47124 | I26: =I72 -> 0 | J26: =J72 -> 0 | K26: =K72 -> 0 | L26: =L72 -> 0 | M26: =M72 -> 0 | N26: =N72 -> 0 | ... P26: =P72 -> 0 | Q26: =SUM(G26:P26) -> 99484
B27: AANR excl VTS | C27: =(Q40-Q32)/C15 -> 396627 | F27: Other Fees (e.g. Alias Directory) | Q27: =SUM(G27:P27) -> 0
B28: Incentive $ of Gross Rev. incl VAT | C28: =IFERROR(C24/C23,0) -> 0 | F28: VIK Revenues | G28: =-G36/1.2 -> 0 | H28: =-H36/1.2 -> 0 | I28: =-I36/1.2 -> 0 | J28: =-J36/1.2 -> 0 | K28: =-K36/1.2 -> 0 | L28: =-L36/1.2 -> 0 | M28: =-M36/1.2 -> 0 | N28: =-N36/1.2 -> 0 | ... P28: =-P36/1.2 -> 0 | Q28: =SUM(G28:P28) -> 0
B29: Incentive $ of Core Fees excl IRR VAT | C29: =IFERROR((C24-Q38)/C22,0) -> 0 | F29: FX Spread - Inter | G29: =[1]Calcs!BJ71 -> 0 | H29: =[1]Calcs!BK71 -> 0 | I29: =[1]Calcs!BL71 -> 0 | J29: =[1]Calcs!BM71 -> 0 | K29: =[1]Calcs!BN71 -> 0 | L29: =[1]Calcs!BO71 -> 0 | M29: =[1]Calcs!BP71 -> 0 | N29: =[1]Calcs!BQ71 -> 0 | ... P29: =[1]Calcs!BS71 -> 0 | Q29: =SUM(G29:P29) -> 0
B30: IRR VAT Rate | C30: 0.0277 | F30: FX Spread - Intra | G30: =[1]Calcs!BJ69+[1]Calcs!BJ70 -> 0 | H30: =[1]Calcs!BK69+[1]Calcs!BK70 -> 0 | I30: =[1]Calcs!BL69+[1]Calcs!BL70 -> 0 | J30: =[1]Calcs!BM69+[1]Calcs!BM70 -> 0 | K30: =[1]Calcs!BN69+[1]Calcs!BN70 -> 0 | L30: =[1]Calcs!BO69+[1]Calcs!BO70 -> 0 | M30: =[1]Calcs!BP69+[1]Calcs!BP70 -> 0 | N30: =[1]Calcs!BQ69+[1]Calcs!BQ70 -> 0 | ... P30: =[1]Calcs!BS69+[1]Calcs!BS70 -> 0 | Q30: =SUM(G30:P30) -> 0
B31: IRR VAT Rate | C31: 0.0277 | F31: Visa+ | G31: =SUM([1]Calcs!AC84,[1]Calcs!AC90)*[1]Calcs!$B$4 -> 0 | H31: =SUM([1]Calcs!AD84,[1]Calcs!AD90)*[1]Calcs!$B$4 -> 0 | I31: =SUM([1]Calcs!AE84,[1]Calcs!AE90)*[1]Calcs!$B$4 -> 0 | J31: =SUM([1]Calcs!AF84,[1]Calcs!AF90)*[1]Calcs!$B$4 -> 0 | K31: =SUM([1]Calcs!AG84,[1]Calcs!AG90)*[1]Calcs!$B$4 -> 0 | L31: =SUM([1]Calcs!AH84,[1]Calcs!AH90)*[1]Calcs!$B$4 -> 0 | M31: =SUM([1]Calcs!AI84,[1]Calcs!AI90)*[1]Calcs!$B$4 -> 0 | N31: =SUM([1]Calcs!AJ84,[1]Calcs!AJ90)*[1]Calcs!$B$4 -> 0 | ... P31: =SUM([1]Calcs!AL84,[1]Calcs!AL90)*[1]Calcs!$B$4 -> 0 | Q31: =SUM(G31:P31) -> 0
B32: Deal Breakeven | C32: =Q74 -> 1 | F32: Delegated Auth Fees (3DS/VTS) | G32: =Inputs!E52*[1]Calcs!$B$3 -> 65450 | H32: =Inputs!F52*[1]Calcs!$B$3 -> 65450 | I32: =Inputs!G52*[1]Calcs!$B$3 -> 0 | J32: =Inputs!H52*[1]Calcs!$B$3 -> 0 | K32: =Inputs!I52*[1]Calcs!$B$3 -> 0 | L32: =Inputs!J52*[1]Calcs!$B$3 -> 0 | M32: =Inputs!K52*[1]Calcs!$B$3 -> 0 | N32: =Inputs!L52*[1]Calcs!$B$3 -> 0 | ... P32: =Inputs!N52*[1]Calcs!$B$3 -> 0 | Q32: =SUM(G32:P32) -> 130900 | R32: =G20/G10 -> 0.0448 | S32: =H20/H10 -> 0.0448 | T32: =I20/I10 -> #DIV/0!
B33: Upfront | C33: =Q34 -> 0 | E33: Incentives | F33: Total Incentives (incl VAT) | G33: =SUM(G34:G38) -> 0 | H33: =SUM(H34:H38) -> 0 | I33: =SUM(I34:I38) -> 0 | J33: =SUM(J34:J38) -> 0 | K33: =SUM(K34:K38) -> 0 | L33: =SUM(L34:L38) -> 0 | M33: =SUM(M34:M38) -> 0 | N33: =SUM(N34:N38) -> 0 | ... Q33: =SUM(Q34:Q38) -> 0
B34: Fixed Support | C34: =Q35+Q36 -> 0 | F34: Upfront (Max $250k incl VAT) - earned out | Q34: =SUM(G34:P34) -> 0
B35: Volume Support | C35: =Q37 -> 0 | F35: Fixed Support - earned out | Q35: =SUM(G35:P35) -> 0
B36: Total Incentive Value | C36: =SUM(C33:C35) -> 0 | F36: VIK Support (Gross, including VAT) - earned out | Q36: =SUM(G36:P36) -> 0
B37: Please review the RED cells as these indicate an error | F37: Volume Support (milestone based) | G37: =IF((0.06*G10)-G20>0,0,(0.06*G10)-G20) -> 0 | H37: =IF((0.06*H10)-H20>0,0,(0.06*H10)-H20) -> 0 | I37: =(0.06*I10)-I20 -> 0 | J37: =(0.05*J10)-J20 -> 0 | K37: =(0.05*K10)-K20 -> 0 | L37: =(0.05*L10)-L20 -> 0 | Q37: =SUM(G37:P37) -> 0
B38: Select Incetive structure option below Note: All Options include earnout of Upfront, VIK and Fixed Incentives | F38: VAT on Merchant Support | G38: =SUM(G34:G35,G37)*$C$30 -> 0 | H38: =SUM(H34:H35,H37)*$C$30 -> 0 | I38: =SUM(I34:I35,I37)*$C$30 -> 0 | J38: =SUM(J34:J35,J37)*$C$30 -> 0 | K38: =SUM(K34:K35,K37)*$C$30 -> 0 | L38: =SUM(L34:L35,L37)*$C$30 -> 0 | M38: =SUM(M34:M35,M37)*$C$30 -> 0 | N38: =SUM(N34:N35,N37)*$C$30 -> 0 | ... P38: =SUM(P34:P35,P37)*$C$30 -> 0 | Q38: =SUM(G38:P38) -> 0
E40: Net Revenue | G40: =G18+G33 -> 464695 | H40: =H18+H33 -> 459459 | I40: =I18+I33 -> 0 | J40: =J18+J33 -> 0 | K40: =K18+K33 -> 0 | L40: =L18+L33 -> 0 | M40: =M18+M33 -> 0 | N40: =N18+N33 -> 0 | ... P40: =P18+P33 -> 0 | Q40: =SUM(G40:P40) -> 924154
E41: Cumulative Net Revenue | G41: =G40 -> 464695 | H41: =G41+H40 -> 924154 | I41: =H41+I40 -> 924154 | J41: =I41+J40 -> 924154 | K41: =J41+K40 -> 924154 | L41: =K41+L40 -> 924154 | M41: =L41+M40 -> 924154 | N41: =M41+N40 -> 924154 | O41: =N41+O40 -> 924154 | P41: =O41+P40 -> 924154 | Q41: =Q40 -> 924154
E43: Variable Costs | G43: =G44+G45+G46 -> -17167.535 | H43: =H44+H45+H46 -> -15838.9 | I43: =I44+I45+I46 -> 0 | J43: =J44+J45+J46 -> 0 | K43: =K44+K45+K46 -> 0 | L43: =L44+L45+L46 -> 0 | M43: =M44+M45+M46 -> 0 | N43: =N44+N45+N46 -> 0 | ... P43: =P44+P45+P46 -> 0 | Q43: =SUM(G43:P43) -> -33006.435
F44: Auth | G44: =-G$7*G$63 -> -9139.8989 | H44: =-H$7*H$63 -> -8432.5411 | I44: =-I$7*I$63 -> 0 | J44: =-J$7*J$63 -> 0 | K44: =-K$7*K$63 -> 0 | L44: =-L$7*L$63 -> 0 | M44: =-M$7*M$63 -> 0 | N44: =-N$7*N$63 -> 0 | ... P44: =-P$7*P$63 -> 0 | Q44: =SUM(G44:P44) -> -17572.44
F45: C&S | G45: =-G$7*G$64 -> -8027.6361 | H45: =-H$7*H$64 -> -7406.3589 | I45: =-I$7*I$64 -> 0 | J45: =-J$7*J$64 -> 0 | K45: =-K$7*K$64 -> 0 | L45: =-L$7*L$64 -> 0 | M45: =-M$7*M$64 -> 0 | N45: =-N$7*N$64 -> 0 | ... P45: =-P$7*P$64 -> 0 | Q45: =SUM(G45:P45) -> -15433.995 | S45: =0.034*0.8 -> 0.0272
E46: 0.75 | F46: VIK Costs | G46: =-G28*$E$46 -> 0 | H46: =-H28*$E$46 -> 0 | I46: =-I28*$E$46 -> 0 | J46: =-J28*$E$46 -> 0 | K46: =-K28*$E$46 -> 0 | L46: =-L28*$E$46 -> 0 | M46: =-M28*$E$46 -> 0 | N46: =-N28*$E$46 -> 0 | ... P46: =-P28*$E$46 -> 0 | Q46: =SUM(G46:P46) -> 0 | S46: 0.025
E47: Contribution | G47: =G43+G40 -> 447527.46 | H47: =H43+H40 -> 443620.1 | I47: =I43+I40 -> 0 | J47: =J43+J40 -> 0 | K47: =K43+K40 -> 0 | L47: =L43+L40 -> 0 | M47: =M43+M40 -> 0 | N47: =N43+N40 -> 0 | ... P47: =P43+P40 -> 0 | Q47: =SUM(G47:P47) -> 891147.56
E48: Cumulative Contribution | G48: =G47 -> 447527.46 | H48: =G48+H47 -> 891147.56 | I48: =H48+I47 -> 891147.56 | J48: =I48+J47 -> 891147.56 | K48: =J48+K47 -> 891147.56 | L48: =K48+L47 -> 891147.56 | M48: =L48+M47 -> 891147.56 | N48: =M48+N47 -> 891147.56 | O48: =N48+O47 -> 891147.56 | P48: =O48+P47 -> 891147.56 | Q48: =Q47 -> 891147.56
E50: Cumulative NPV | G50: =G56 -> 406843.15 | H50: =H56 -> 773471.33 | I50: =I56 -> 773471.33 | J50: =J56 -> 773471.33 | K50: =K56 -> 773471.33 | L50: =L56 -> 773471.33 | M50: =M56 -> 773471.33 | N50: =N56 -> 773471.33 | ... P50: =P56 -> 773471.33 | Q50: =P50 -> 773471.33
E52: Per Transaction Yield | G52: =IFERROR(G40/G7,0) -> 0.071 | H52: =IFERROR(H40/H7,0) -> 0.0702 | I52: =IFERROR(I40/I7,0) -> 0 | J52: =IFERROR(J40/J7,0) -> 0 | K52: =IFERROR(K40/K7,0) -> 0 | L52: =IFERROR(L40/L7,0) -> 0 | M52: =IFERROR(M40/M7,0) -> 0 | N52: =IFERROR(N40/N7,0) -> 0 | ... Q52: =IFERROR(Q40/Q7,0) -> 0.0706
E53: NRY (on PV) | G53: =IFERROR(G40/G6*10000,0) -> 4.4375 | H53: =IFERROR(H40/H6*10000,0) -> 4.3875 | I53: =IFERROR(I40/I6*10000,0) -> 0 | J53: =IFERROR(J40/J6*10000,0) -> 0 | K53: =IFERROR(K40/K6*10000,0) -> 0 | L53: =IFERROR(L40/L6*10000,0) -> 0 | M53: =IFERROR(M40/M6*10000,0) -> 0 | N53: =IFERROR(N40/N6*10000,0) -> 0 | ... Q53: =IFERROR(Q40/Q6*10000,0) -> 4.4125
E54: Cumulative NRY (on PV) | G54: =IFERROR(SUM($G$40:G40)/SUM($G$6:G6)*10000,"") -> 4.4375 | H54: =IFERROR(SUM($G$40:H40)/SUM($G$6:H6)*10000,"") -> 4.4125 | I54: =IFERROR(SUM($G$40:I40)/SUM($G$6:I6)*10000,"") -> 4.4125 | J54: =IFERROR(SUM($G$40:J40)/SUM($G$6:J6)*10000,"") -> 4.4125 | K54: =IFERROR(SUM($G$40:K40)/SUM($G$6:K6)*10000,"") -> 4.4125 | L54: =IFERROR(SUM($G$40:L40)/SUM($G$6:L6)*10000,"") -> 4.4125 | M54: =IFERROR(SUM($G$40:M40)/SUM($G$6:M6)*10000,"") -> 4.4125 | N54: =IFERROR(SUM($G$40:N40)/SUM($G$6:N6)*10000,"") -> 4.4125 | ... P54: =IFERROR(SUM($G$40:P40)/SUM($G$6:P6)*10000,"") -> 4.4125 | Q54: =P54 -> 4.4125
E56: NPV (Cumulative) | G56: =G61 -> 406843.15 | H56: =H61 -> 773471.33 | I56: =I61 -> 773471.33 | J56: =J61 -> 773471.33 | K56: =K61 -> 773471.33 | L56: =L61 -> 773471.33 | M56: =M61 -> 773471.33 | N56: =N61 -> 773471.33 | ... Q56: =Q61 -> 773471.33
G58: 1 | H58: 2 | I58: 3 | J58: 4 | K58: 5 | L58: 6 | M58: 7 | N58: 8 | O58: 9 | P58: 10
F59: 1 | G59: =(1+$E$60)^-G58 -> 0.90909091 | H59: =(1+$E$60)^-H58 -> 0.82644628 | I59: =(1+$E$60)^-I58 -> 0.7513148 | J59: =(1+$E$60)^-J58 -> 0.68301346 | K59: =(1+$E$60)^-K58 -> 0.62092132 | L59: =(1+$E$60)^-L58 -> 0.56447393 | M59: =(1+$E$60)^-M58 -> 0.51315812 | N59: =(1+$E$60)^-N58 -> 0.46650738 | ... P59: =(1+$E$60)^-P58 -> 0.38554329
E60: 0.1 | F60: =G34 -> 0 | G60: =G59*SUM(G35:G38,G18,G43) -> 406843.15 | H60: =H59*SUM(H35:H38,H18,H43) -> 366628.18 | I60: =I59*SUM(I35:I38,I18,I43) -> 0 | J60: =J59*SUM(J35:J38,J18,J43) -> 0 | K60: =K59*SUM(K35:K38,K18,K43) -> 0 | L60: =L59*SUM(L35:L38,L18,L43) -> 0 | M60: =M59*SUM(M35:M38,M18,M43) -> 0 | N60: =N59*SUM(N35:N38,N18,N43) -> 0 | ... P60: =P59*SUM(P35:P38,P18,P43) -> 0 | Q60: =SUM(F60:P60) -> 773471.33
E61: NPV | F61: =F60 -> 0 | G61: =F61+G60 -> 406843.15 | H61: =G61+H60 -> 773471.33 | I61: =H61+I60 -> 773471.33 | J61: =I61+J60 -> 773471.33 | K61: =J61+K60 -> 773471.33 | L61: =K61+L60 -> 773471.33 | M61: =L61+M60 -> 773471.33 | N61: =M61+N60 -> 773471.33 | ... P61: =O61+P60 -> 773471.33 | Q61: =IFERROR(HLOOKUP($C$15,$G$58:$P$61,4,0),0) -> 773471.33
E63: 0.53239437 | F63: Auth | G63: =G$65*$E63 -> 0.0013964704 | H63: =H$65*$E63 -> 0.0012883944 | I63: =I$65*$E63 -> 0.0012074704 | J63: =J$65*$E63 -> 0.0011419859 | K63: =K$65*$E63 -> 0.0010860845 | L63: =L$65*$E63 -> 0.0010360394 | M63: =M$65*$E63 -> 0.00099025352 | N63: =N$65*$E63 -> 0.00094819437 | ... P63: =P$65*$E63 -> 0.00094819437
E64: 0.46760563 | F64: C&S | G64: =G$65*$E64 -> 0.0012265296 | H64: =H$65*$E64 -> 0.0011316056 | I64: =I$65*$E64 -> 0.0010605296 | J64: =J$65*$E64 -> 0.0010030141 | K64: =K$65*$E64 -> 0.00095391549 | L64: =L$65*$E64 -> 0.00090996056 | M64: =M$65*$E64 -> 0.00086974648 | N64: =N$65*$E64 -> 0.00083280563 | ... P64: =P$65*$E64 -> 0.00083280563
F65: Total Variable Processing Costs | G65: 0.002623 | H65: 0.00242 | I65: 0.002268 | J65: 0.002145 | K65: 0.00204 | L65: 0.001946 | M65: 0.00186 | N65: 0.001781 | O65: 0.001781 | P65: 0.001781
F66: Core Fees | G66: =SUM(G19,G20,G22,G23,G25) -> 346885 | H66: =SUM(H19,H20,H22,H23,H25) -> 346885 | I66: =SUM(I19,I20,I22,I23,I25) -> 0 | J66: =SUM(J19,J20,J22,J23,J25) -> 0 | K66: =SUM(K19,K20,K22,K23,K25) -> 0 | L66: =SUM(L19,L20,L22,L23,L25) -> 0 | M66: =SUM(M19,M20,M22,M23,M25) -> 0 | N66: =SUM(N19,N20,N22,N23,N25) -> 0 | ... P66: =SUM(P19,P20,P22,P23,P25) -> 0 | Q66: =SUM(G66:P66) -> 693770
F67: Amortized Discount | G67: =-$G$2*G66 -> 0 | H67: =-$G$2*H66 -> 0 | I67: =-$G$2*I66 -> 0 | J67: =-$G$2*J66 -> 0 | K67: =-$G$2*K66 -> 0 | L67: =-$G$2*L66 -> 0 | M67: =-$G$2*M66 -> 0 | N67: =-$G$2*N66 -> 0 | ... P67: =-$G$2*P66 -> 0 | Q67: =SUM(G67:P67) -> 0
E68: OCT only (destination) | F68: Net Issuing Yield (Please Update for Market) | G68: 0.5 | H68: =G68*0.9 -> 0.45 | I68: =H68*0.9 -> 0.405 | J68: =I68*0.9 -> 0.3645 | K68: =J68*0.9 -> 0.32805 | L68: =K68*0.9 -> 0.295245 | M68: =L68*0.9 -> 0.2657205 | N68: =M68*0.9 -> 0.23914845 | O68: =N68*0.9 -> 0.21523361 | P68: =O68*0.9 -> 0.19371024
E69: AFT Only (originator market) | F69: Net Issuing Yield (Please Update for Market) | G69: 0.5 | H69: =G69*0.9 -> 0.45 | I69: =H69*0.9 -> 0.405 | J69: =I69*0.9 -> 0.3645 | K69: =J69*0.9 -> 0.32805 | L69: =K69*0.9 -> 0.295245 | M69: =L69*0.9 -> 0.2657205 | N69: =M69*0.9 -> 0.23914845 | O69: =N69*0.9 -> 0.21523361 | P69: =O69*0.9 -> 0.19371024
F70: OCT PV (DOM, IntraEEA, Intra NonEEA) | G70: =Inputs!E21+Inputs!E22+Inputs!E23+Inputs!E34+Inputs!E35+Inputs!E36 -> 0 | H70: =Inputs!F21+Inputs!F22+Inputs!F23+Inputs!F34+Inputs!F35+Inputs!F36 -> 0 | I70: =Inputs!G21+Inputs!G22+Inputs!G23+Inputs!G34+Inputs!G35+Inputs!G36 -> 0 | J70: =Inputs!H21+Inputs!H22+Inputs!H23+Inputs!H34+Inputs!H35+Inputs!H36 -> 0 | K70: =Inputs!I21+Inputs!I22+Inputs!I23+Inputs!I34+Inputs!I35+Inputs!I36 -> 0 | L70: =Inputs!J21+Inputs!J22+Inputs!J23+Inputs!J34+Inputs!J35+Inputs!J36 -> 0 | M70: =Inputs!K21+Inputs!K22+Inputs!K23+Inputs!K34+Inputs!K35+Inputs!K36 -> 0 | N70: =Inputs!L21+Inputs!L22+Inputs!L23+Inputs!L34+Inputs!L35+Inputs!L36 -> 0 | ... P70: =Inputs!N21+Inputs!N22+Inputs!N23+Inputs!N34+Inputs!N35+Inputs!N36 -> 0
F71: AFT PV (DOM, IntraEEA, Intra NonEEA) | G71: =SUM(Inputs!E47:E49) -> 1047200000 | H71: =SUM(Inputs!F47:F49) -> 1047200000 | I71: =SUM(Inputs!G47:G49) -> 0 | J71: =SUM(Inputs!H47:H49) -> 0 | K71: =SUM(Inputs!I47:I49) -> 0 | L71: =SUM(Inputs!J47:J49) -> 0 | M71: =SUM(Inputs!K47:K49) -> 0 | N71: =SUM(Inputs!L47:L49) -> 0 | ... P71: =SUM(Inputs!N47:N49) -> 0
F72: Total NS Issuing Fees | G72: =(G68*G70/10000)+(G69*G71/10000) -> 52360 | H72: =(H68*H70/10000)+(H69*H71/10000) -> 47124 | I72: =(I68*I70/10000)+(I69*I71/10000) -> 0 | J72: =(J68*J70/10000)+(J69*J71/10000) -> 0 | K72: =(K68*K70/10000)+(K69*K71/10000) -> 0 | L72: =(L68*L70/10000)+(L69*L71/10000) -> 0 | M72: =(M68*M70/10000)+(M69*M71/10000) -> 0 | N72: =(N68*N70/10000)+(N69*N71/10000) -> 0 | ... P72: =(P68*P70/10000)+(P69*P71/10000) -> 0
F73: Assessing Deal Term Contribution | G73: =IF(G58<=$C$15,IF(SUM($G$47:G47)>0,1,0),0) -> 1 | H73: =IF(H58<=$C$15,IF(SUM($G$47:H47)>0,1,0),0) -> 1 | I73: =IF(I58<=$C$15,IF(SUM($G$47:I47)>0,1,0),0) -> 0 | J73: =IF(J58<=$C$15,IF(SUM($G$47:J47)>0,1,0),0) -> 0 | K73: =IF(K58<=$C$15,IF(SUM($G$47:K47)>0,1,0),0) -> 0 | L73: =IF(L58<=$C$15,IF(SUM($G$47:L47)>0,1,0),0) -> 0 | M73: =IF(M58<=$C$15,IF(SUM($G$47:M47)>0,1,0),0) -> 0 | N73: =IF(N58<=$C$15,IF(SUM($G$47:N47)>0,1,0),0) -> 0 | ... P73: =IF(P58<=$C$15,IF(SUM($G$47:P47)>0,1,0),0) -> 0 | Q73: =IF(SUM(G73:P73)<C15,0,1) -> 1 | S73: =IF(Q73=0,"Check - does not break even","OK") -> OK
E74: Breakeven Year based on Contribution (Cash flow) | G74: =IF(SUM($G$47:G47)>0,1,0) -> 1 | H74: =IF(SUM($G$74:G74)=1,0,IF(SUM($G$47:H47)>0,1,0)) -> 0 | I74: =IF(SUM($G$74:H74)=1,0,IF(SUM($G$47:I47)>0,1,0)) -> 0 | J74: =IF(SUM($G$74:I74)=1,0,IF(SUM($G$47:J47)>0,1,0)) -> 0 | K74: =IF(SUM($G$74:J74)=1,0,IF(SUM($G$47:K47)>0,1,0)) -> 0 | L74: =IF(SUM($G$74:K74)=1,0,IF(SUM($G$47:L47)>0,1,0)) -> 0 | M74: =IF(SUM($G$74:L74)=1,0,IF(SUM($G$47:M47)>0,1,0)) -> 0 | N74: =IF(SUM($G$74:M74)=1,0,IF(SUM($G$47:N47)>0,1,0)) -> 0 | O74: =IF(SUM($G$74:N74)=1,0,IF(SUM($G$47:O47)>0,1,0)) -> 0 | P74: =IF(SUM($G$74:O74)=1,0,IF(SUM($G$47:P47)>0,1,0)) -> 0 | Q74: =IF(SUM(G74:P74)>1,"Error",MATCH(1,G74:P74,0)) -> 1
N75: Check with finance to change tiers
N76: Option 2 Discount Table
G77: Core Revenue Split by Prod | H77: % Split | I77: %Split Over ride | N77: XB OCT Txns from | O77: XB OCT Txns to | P77: Discount on Core XB OCTFees
E78: OCT P2P DOM | G78: =SUM([1]Calcs!AN104:AW104) -> 0 | H78: =IF(I78=0,G78/SUM($G$78:$G$86),I78) -> 0 | I78: 0 | N78: 0 | O78: 99999 | P78: 0
E79: OCT P2P Intra | G79: =SUM([1]Calcs!AN105:AW105) -> 0 | H79: =IF(I79=0,G79/SUM($G$78:$G$86),I79) -> 0 | I79: 0 | N79: =O78+1 -> 100000 | O79: 499999 | P79: 0.1
E80: OCT P2P Inter | G80: =SUM([1]Calcs!AN106:AW107) -> 0 | H80: =IF(I80=0,G80/SUM($G$78:$G$86),I80) -> 0 | I80: 0 | N80: =O79+1 -> 500000 | O80: 1499999 | P80: 0.2
E81: OCT FD DOM | G81: =SUM([1]Calcs!AN98:AW98) -> 0 | H81: =IF(I81=0,G81/SUM($G$78:$G$86),I81) -> 0 | I81: 0 | N81: =O80+1 -> 1500000 | O81: 2999999 | P81: 0.25
E82: OCT FD Intra | G82: =SUM([1]Calcs!AN99:AW99) -> 0 | H82: =IF(I82=0,G82/SUM($G$78:$G$86),I82) -> 0 | I82: 0 | N82: =O81+1 -> 3000000 | O82: Uncapped | P82: 0.3
E83: OCT FD Inter | G83: =SUM([1]Calcs!AN100:AW101) -> 0 | H83: =IF(I83=0,G83/SUM($G$78:$G$86),I83) -> 0 | I83: 0
E84: AFT DOM | G84: =SUM([1]Calcs!AN92:AW92) -> 693770 | H84: =IF(I84=0,G84/SUM($G$78:$G$86),I84) -> 1 | I84: 0
E85: AFT Intra | G85: =SUM([1]Calcs!AN93:AW93) -> 0 | H85: =IF(I85=0,G85/SUM($G$78:$G$86),I85) -> 0 | I85: 0 | N85: Option 3 Discount Table, use with XB table above
E86: AFT Inter | G86: =SUM([1]Calcs!AN94:AW95) -> 0 | H86: =IF(I86=0,G86/SUM($G$78:$G$86),I86) -> 0 | I86: 0 | N86: DOM/Intra OCT From | O86: DOM/Intra OCT To | P86: Discount on Total Core Fees
N87: 0 | O87: 500000 | P87: 0
N88: =O87+1 -> 500001 | O88: 1500000 | P88: 0.1
N89: =O88+1 -> 1500001 | O89: 3000000 | P89: 0.125
N90: =O89+1 -> 3000001 | O90: 5000000 | P90: 0.15
N91: =O90+1 -> 5000001 | O91: 50000000 | P91: 0.2
E97: BELOW INCENTIVE CALC
E98: XB OCT Txn | G98: =Inputs!E30+Inputs!E43+Inputs!E29+Inputs!E42 -> 0 | H98: =Inputs!F30+Inputs!F43+Inputs!F29+Inputs!F42 -> 0 | I98: =Inputs!G30+Inputs!G43+Inputs!G29+Inputs!G42 -> 0 | J98: =Inputs!H30+Inputs!H43+Inputs!H29+Inputs!H42 -> 0 | K98: =Inputs!I30+Inputs!I43+Inputs!I29+Inputs!I42 -> 0 | L98: =Inputs!J30+Inputs!J43+Inputs!J29+Inputs!J42 -> 0 | M98: =Inputs!K30+Inputs!K43+Inputs!K29+Inputs!K42 -> 0 | N98: =Inputs!L30+Inputs!L43+Inputs!L29+Inputs!L42 -> 0 | ... P98: =Inputs!N30+Inputs!N43+Inputs!N29+Inputs!N42 -> 0
E99: XB OCT PV | G99: =Inputs!E23+Inputs!E24+Inputs!E36+Inputs!E37 -> 0 | H99: =Inputs!F23+Inputs!F24+Inputs!F36+Inputs!F37 -> 0 | I99: =Inputs!G23+Inputs!G24+Inputs!G36+Inputs!G37 -> 0 | J99: =Inputs!H23+Inputs!H24+Inputs!H36+Inputs!H37 -> 0 | K99: =Inputs!I23+Inputs!I24+Inputs!I36+Inputs!I37 -> 0 | L99: =Inputs!J23+Inputs!J24+Inputs!J36+Inputs!J37 -> 0 | M99: =Inputs!K23+Inputs!K24+Inputs!K36+Inputs!K37 -> 0 | N99: =Inputs!L23+Inputs!L24+Inputs!L36+Inputs!L37 -> 0 | ... P99: =Inputs!N23+Inputs!N24+Inputs!N36+Inputs!N37 -> 0
E100: XB OCT Fee discount | G100: =VLOOKUP(G98,$N$78:$P$83,3,1) -> 0 | H100: =VLOOKUP(H98,$N$78:$P$83,3,1) -> 0 | I100: =VLOOKUP(I98,$N$78:$P$83,3,1) -> 0 | J100: =VLOOKUP(J98,$N$78:$P$83,3,1) -> 0 | K100: =VLOOKUP(K98,$N$78:$P$83,3,1) -> 0 | L100: =VLOOKUP(L98,$N$78:$P$83,3,1) -> 0 | M100: =VLOOKUP(M98,$N$78:$P$83,3,1) -> 0 | N100: =VLOOKUP(N98,$N$78:$P$83,3,1) -> 0 | ... P100: =VLOOKUP(P98,$N$78:$P$83,3,1) -> 0
E101: Incentive on XB OCT | G101: =-G100*G25 -> 0 | H101: =-H100*H25 -> 0 | I101: =-I100*I25 -> 0 | J101: =-J100*J25 -> 0 | K101: =-K100*K25 -> 0 | L101: =-L100*L25 -> 0 | M101: =-M100*M25 -> 0 | N101: =-N100*N25 -> 0 | ... P101: =-P100*P25 -> 0
E103: DOM/Intra OCT Txns | G103: =Inputs!E27+Inputs!E28+Inputs!E40+Inputs!E41 -> 0 | H103: =Inputs!F27+Inputs!F28+Inputs!F40+Inputs!F41 -> 0 | I103: =Inputs!G27+Inputs!G28+Inputs!G40+Inputs!G41 -> 0 | J103: =Inputs!H27+Inputs!H28+Inputs!H40+Inputs!H41 -> 0 | K103: =Inputs!I27+Inputs!I28+Inputs!I40+Inputs!I41 -> 0 | L103: =Inputs!J27+Inputs!J28+Inputs!J40+Inputs!J41 -> 0 | M103: =Inputs!K27+Inputs!K28+Inputs!K40+Inputs!K41 -> 0 | N103: =Inputs!L27+Inputs!L28+Inputs!L40+Inputs!L41 -> 0 | ... P103: =Inputs!N27+Inputs!N28+Inputs!N40+Inputs!N41 -> 0
E104: DOM/Intra OCT Fee discount | G104: =VLOOKUP(G103,$N$87:$P$91,3,1) -> 0 | H104: =VLOOKUP(H103,$N$87:$P$91,3,1) -> 0 | I104: =VLOOKUP(I103,$N$87:$P$91,3,1) -> 0 | J104: =VLOOKUP(J103,$N$87:$P$91,3,1) -> 0 | K104: =VLOOKUP(K103,$N$87:$P$91,3,1) -> 0 | L104: =VLOOKUP(L103,$N$87:$P$91,3,1) -> 0 | M104: =VLOOKUP(M103,$N$87:$P$91,3,1) -> 0 | N104: =VLOOKUP(N103,$N$87:$P$91,3,1) -> 0 | ... P104: =VLOOKUP(P103,$N$87:$P$91,3,1) -> 0
E105: Incentive on DOM/Intra OCT | G105: =-G104*SUM([1]Calcs!AN98:AN99,[1]Calcs!AN104:AN105) -> 0 | H105: =-H104*SUM([1]Calcs!AO98:AO99,[1]Calcs!AO104:AO105) -> 0 | I105: =-I104*SUM([1]Calcs!AP98:AP99,[1]Calcs!AP104:AP105) -> 0 | J105: =-J104*SUM([1]Calcs!AQ98:AQ99,[1]Calcs!AQ104:AQ105) -> 0 | K105: =-K104*SUM([1]Calcs!AR98:AR99,[1]Calcs!AR104:AR105) -> 0 | L105: =-L104*SUM([1]Calcs!AS98:AS99,[1]Calcs!AS104:AS105) -> 0 | M105: =-M104*SUM([1]Calcs!AT98:AT99,[1]Calcs!AT104:AT105) -> 0 | N105: =-N104*SUM([1]Calcs!AU98:AU99,[1]Calcs!AU104:AU105) -> 0 | ... P105: =-P104*SUM([1]Calcs!AW98:AW99,[1]Calcs!AW104:AW105) -> 0
E108: Select Incentive Option
E109: Option 1 (Input Flat Discount %, excludes AFT) | G109: =-SUM([1]Calcs!AN102,[1]Calcs!AN108)*'P&L'!$G$2 -> 0 | H109: =-SUM([1]Calcs!AO102,[1]Calcs!AO108)*'P&L'!$G$2 -> 0 | I109: =-SUM([1]Calcs!AP102,[1]Calcs!AP108)*'P&L'!$G$2 -> 0 | J109: =-SUM([1]Calcs!AQ102,[1]Calcs!AQ108)*'P&L'!$G$2 -> 0 | K109: =-SUM([1]Calcs!AR102,[1]Calcs!AR108)*'P&L'!$G$2 -> 0 | L109: =-SUM([1]Calcs!AS102,[1]Calcs!AS108)*'P&L'!$G$2 -> 0 | M109: =-SUM([1]Calcs!AT102,[1]Calcs!AT108)*'P&L'!$G$2 -> 0 | N109: =-SUM([1]Calcs!AU102,[1]Calcs!AU108)*'P&L'!$G$2 -> 0 | ... P109: =-SUM([1]Calcs!AW102,[1]Calcs!AW108)*'P&L'!$G$2 -> 0
E110: Option 2 (Only XB OCTs, tiered discount) | G110: =G101 -> 0 | H110: =H101 -> 0 | I110: =I101 -> 0 | J110: =J101 -> 0 | K110: =K101 -> 0 | L110: =L101 -> 0 | M110: =M101 -> 0 | N110: =N101 -> 0 | ... P110: =P101 -> 0
E111: Option 3 (Tiered DOM/Intra OCT, Tiered XB OCT) | G111: =G105+G101 -> 0 | H111: =H105+H101 -> 0 | I111: =I105+I101 -> 0 | J111: =J105+J101 -> 0 | K111: =K105+K101 -> 0 | L111: =L105+L101 -> 0 | M111: =M105+M101 -> 0 | N111: =N105+N101 -> 0 | ... P111: =P105+P101 -> 0
E115: Only for option 1 | G115: 3 | H115: 4 | I115: 5 | J115: 6 | K115: 7 | L115: 8 | M115: 9 | N115: 10 | O115: 11 | P115: 12
E116: Final Discount as per Option | G116: =VLOOKUP($F$2,$E$109:$P$111,G115,0) -> 0 | H116: =VLOOKUP($F$2,$E$109:$P$111,H115,0) -> 0 | I116: =VLOOKUP($F$2,$E$109:$P$111,I115,0) -> 0 | J116: =VLOOKUP($F$2,$E$109:$P$111,J115,0) -> 0 | K116: =VLOOKUP($F$2,$E$109:$P$111,K115,0) -> 0 | L116: =VLOOKUP($F$2,$E$109:$P$111,L115,0) -> 0 | M116: =VLOOKUP($F$2,$E$109:$P$111,M115,0) -> 0 | N116: =VLOOKUP($F$2,$E$109:$P$111,N115,0) -> 0 | ... P116: =VLOOKUP($F$2,$E$109:$P$111,P115,0) -> 0
E117: DOM/Intra | G117: =G116-G118 -> 0 | H117: =H116-H118 -> 0 | I117: =I116-I118 -> 0 | J117: =J116-J118 -> 0 | K117: =K116-K118 -> 0 | L117: =L116-L118 -> 0 | M117: =M116-M118 -> 0 | N117: =N116-N118 -> 0 | ... P117: =P116-P118 -> 0
E118: Inter | G118: =IF($F$2=$E$109,-G25*$G$2,IF($F$2=$E$110,G101,G101)) -> 0 | H118: =IF($F$2=$E$109,-H25*$G$2,IF($F$2=$E$110,H101,H101)) -> 0 | I118: =IF($F$2=$E$109,-I25*$G$2,IF($F$2=$E$110,I101,I101)) -> 0 | J118: =IF($F$2=$E$109,-J25*$G$2,IF($F$2=$E$110,J101,J101)) -> 0 | K118: =IF($F$2=$E$109,-K25*$G$2,IF($F$2=$E$110,K101,K101)) -> 0 | L118: =IF($F$2=$E$109,-L25*$G$2,IF($F$2=$E$110,L101,L101)) -> 0 | M118: =IF($F$2=$E$109,-M25*$G$2,IF($F$2=$E$110,M101,M101)) -> 0 | N118: =IF($F$2=$E$109,-N25*$G$2,IF($F$2=$E$110,N101,N101)) -> 0 | ... P118: =IF($F$2=$E$109,-P25*$G$2,IF($F$2=$E$110,P101,P101)) -> 0

Sheet Inputs
A1: EEA | B1: INTRA EEA | D1: Modelling Assumptions | F1: Mandatory Fields | J1: Optional Fields | N1: FX EUR/USD | O1: 1.1135 | R1: Guidance on completing input sheet: 1. Please fill in cells highlighted in Yellow - INPUT in EUROS 2. Please select the Market from the drop down. If multiple markets, please select the biggest market for the opportunity. 3. UK/IS/CH/TK to rest of EU is Intra NON-EEA Transaction (also vice versa). If modelling for UK/IS/CH/TK, there will not be any Intra EEA transactions.
A2: UK | B2: Intra NonEEA
A3: Turkey | F3: Origin Market | G3: =VLOOKUP(Intro!$E$3,[1]Metrics!$B$114:$D$156,3,0) -> UK | H3: Term | I3: =Intro!D18 -> 2 | N3: FX EUR/GBP | O3: 0.83252336
A4: Israel | F4: Client Type | G4: Enabler | H4: AFT IRF | I4: MLP T2 | J4: Please select one option or "Rack"
A5: Switzerland | F5: =IF($G$4="Originator","Input Enabler Name","") | G5: TBC | H5: OCT IRF | I5: Rack | J5: Please select one option or "Rack"
D7: Destination | E7: Average Ticket Size
E8: OCT - PP & AA | F8: OCT - FD | G8: AFT | H8: Cross Curr % | I8: Credit % | J8: Debit %
A9: =$G$3&D9 -> UKDOM | D9: DOM | G9: 160 | J9: =1-I9 -> 1
A10: =$G$3&D10 -> UKINTRA EEA | D10: INTRA EEA | H10: 0.1 | J10: =1-I10 -> 1
A11: =$G$3&D11 -> UKINTRA Non-EEA | D11: INTRA Non-EEA | H11: 0.65 | J11: =1-I11 -> 1
A12: =$G$3&D12 -> UKINTER | D12: INTER | H12: 0.65 | J12: =1-I12 -> 1
A17: Mapping Table - Do not change/delete | D17: Input Number of Transactions by Jurisdiction in Yellow Cells
E18: =IF(E19<=$I$3,1,0) -> 1 | F18: =IF(F19<=$I$3,1,0) -> 1 | G18: =IF(G19<=$I$3,1,0) -> 0 | H18: =IF(H19<=$I$3,1,0) -> 0 | I18: =IF(I19<=$I$3,1,0) -> 0 | J18: =IF(J19<=$I$3,1,0) -> 0 | K18: =IF(K19<=$I$3,1,0) -> 0 | L18: =IF(L19<=$I$3,1,0) -> 0 | ... O18: =IF(O19<=$I$3,1,0) -> 0
D19: OCT - PP & AA | E19: 1 | F19: 2 | G19: 3 | H19: 4 | I19: 5 | J19: 6 | K19: 7 | L19: 8 | M19: 9 | N19: 10 | O19: Total
D20: Total PV | E20: =SUM(E21:E24) -> 0 | F20: =SUM(F21:F24) -> 0 | G20: =SUM(G21:G24) -> 0 | H20: =SUM(H21:H24) -> 0 | I20: =SUM(I21:I24) -> 0 | J20: =SUM(J21:J24) -> 0 | K20: =SUM(K21:K24) -> 0 | L20: =SUM(L21:L24) -> 0 | ... N20: =SUM(N21:N24) -> 0 | O20: =SUM(E20:N20) -> 0
D21: DOM | E21: =E27*$E9 -> 0 | F21: =F27*$E9 -> 0 | G21: =G27*$E9 -> 0 | H21: =H27*$E9 -> 0 | I21: =I27*$E9 -> 0 | J21: =J27*$E9 -> 0 | K21: =K27*$E9 -> 0 | L21: =L27*$E9 -> 0 | ... N21: =N27*$E9 -> 0 | O21: =SUM(E21:N21) -> 0
D22: INTRA EEA | E22: =E28*$E10 -> 0 | F22: =F28*$E10 -> 0 | G22: =G28*$E10 -> 0 | H22: =H28*$E10 -> 0 | I22: =I28*$E10 -> 0 | J22: =J28*$E10 -> 0 | K22: =K28*$E10 -> 0 | L22: =L28*$E10 -> 0 | ... N22: =N28*$E10 -> 0 | O22: =SUM(E22:N22) -> 0
D23: INTRA Non-EEA | E23: =E29*$E11 -> 0 | F23: =F29*$E11 -> 0 | G23: =G29*$E11 -> 0 | H23: =H29*$E11 -> 0 | I23: =I29*$E11 -> 0 | J23: =J29*$E11 -> 0 | K23: =K29*$E11 -> 0 | L23: =L29*$E11 -> 0 | ... N23: =N29*$E11 -> 0 | O23: =SUM(E23:N23) -> 0
D24: INTER | E24: =E30*$E12 -> 0 | F24: =F30*$E12 -> 0 | G24: =G30*$E12 -> 0 | H24: =H30*$E12 -> 0 | I24: =I30*$E12 -> 0 | J24: =J30*$E12 -> 0 | K24: =K30*$E12 -> 0 | L24: =L30*$E12 -> 0 | ... N24: =N30*$E12 -> 0 | O24: =SUM(E24:N24) -> 0
R25: Choose Main and Detailed Use Case for OCT P2P | T25: Secondary (BAI) | U25: Tertiary BAI
D26: Total Transactions | E26: =SUM(E27:E30) -> 0 | F26: =SUM(F27:F30) -> 0 | G26: =SUM(G27:G30) -> 0 | H26: =SUM(H27:H30) -> 0 | I26: =SUM(I27:I30) -> 0 | J26: =SUM(J27:J30) -> 0 | K26: =SUM(K27:K30) -> 0 | L26: =SUM(L27:L30) -> 0 | ... N26: =SUM(N27:N30) -> 0 | O26: =SUM(E26:N26) -> 0 | P26: =O26/SUM($O$26+$O$39+$O$52) -> 0
A27: =$G$3&$D$19&D27 -> UKOCT - PP & AADOM | D27: DOM | O27: =SUM(E27:N27) -> 0
A28: =$G$3&$D$19&D28 -> UKOCT - PP & AAINTRA EEA | D28: INTRA EEA | O28: =SUM(E28:N28) -> 0
A29: =$G$3&$D$19&D29 -> UKOCT - PP & AAINTRA Non-EEA | D29: INTRA Non-EEA | O29: =SUM(E29:N29) -> 0
A30: =$G$3&$D$19&D30 -> UKOCT - PP & AAINTER | D30: INTER | O30: =SUM(E30:N30) -> 0
D32: OCT - FD | E32: 1 | F32: 2 | G32: 3 | H32: 4 | I32: 5 | J32: 6 | K32: 7 | L32: 8 | M32: 9 | N32: 10 | O32: Total
D33: Total PV | E33: =SUM(E34:E37) -> 0 | F33: =SUM(F34:F37) -> 0 | G33: =SUM(G34:G37) -> 0 | H33: =SUM(H34:H37) -> 0 | I33: =SUM(I34:I37) -> 0 | J33: =SUM(J34:J37) -> 0 | K33: =SUM(K34:K37) -> 0 | L33: =SUM(L34:L37) -> 0 | ... N33: =SUM(N34:N37) -> 0 | O33: =SUM(E33:N33) -> 0
D34: DOM | E34: =E40*$F9 -> 0 | F34: =F40*$F9 -> 0 | G34: =G40*$F9 -> 0 | H34: =H40*$F9 -> 0 | I34: =I40*$F9 -> 0 | J34: =J40*$F9 -> 0 | K34: =K40*$F9 -> 0 | L34: =L40*$F9 -> 0 | ... N34: =N40*$F9 -> 0 | O34: =SUM(E34:N34) -> 0
D35: INTRA EEA | E35: =E41*$F10 -> 0 | F35: =F41*$F10 -> 0 | G35: =G41*$F10 -> 0 | H35: =H41*$F10 -> 0 | I35: =I41*$F10 -> 0 | J35: =J41*$F10 -> 0 | K35: =K41*$F10 -> 0 | L35: =L41*$F10 -> 0 | ... N35: =N41*$F10 -> 0 | O35: =SUM(E35:N35) -> 0
D36: INTRA Non-EEA | E36: =E42*$F11 -> 0 | F36: =F42*$F11 -> 0 | G36: =G42*$F11 -> 0 | H36: =H42*$F11 -> 0 | I36: =I42*$F11 -> 0 | J36: =J42*$F11 -> 0 | K36: =K42*$F11 -> 0 | L36: =L42*$F11 -> 0 | ... N36: =N42*$F11 -> 0 | O36: =SUM(E36:N36) -> 0
D37: INTER | E37: =E43*$F12 -> 0 | F37: =F43*$F12 -> 0 | G37: =G43*$F12 -> 0 | H37: =H43*$F12 -> 0 | I37: =I43*$F12 -> 0 | J37: =J43*$F12 -> 0 | K37: =K43*$F12 -> 0 | L37: =L43*$F12 -> 0 | ... N37: =N43*$F12 -> 0 | O37: =SUM(E37:N37) -> 0
R38: Choose Main and Detailed Use Case for OCT FD | T38: Secondary (BAI) | U38: Tertiary BAI
D39: Total Transactions | E39: =SUM(E40:E43) -> 0 | F39: =SUM(F40:F43) -> 0 | G39: =SUM(G40:G43) -> 0 | H39: =SUM(H40:H43) -> 0 | I39: =SUM(I40:I43) -> 0 | J39: =SUM(J40:J43) -> 0 | K39: =SUM(K40:K43) -> 0 | L39: =SUM(L40:L43) -> 0 | ... N39: =SUM(N40:N43) -> 0 | O39: =SUM(E39:N39) -> 0 | P39: =O39/SUM($O$26+$O$39+$O$52) -> 0
A40: =$G$3&$D$32&D40 -> UKOCT - FDDOM | B40: DOM | D40: DOM | O40: =SUM(E40:N40) -> 0
A41: =$G$3&$D$32&D41 -> UKOCT - FDINTRA EEA | B41: INTRA EEA | D41: INTRA EEA | O41: =SUM(E41:N41) -> 0
A42: =$G$3&$D$32&D42 -> UKOCT - FDINTRA Non-EEA | B42: INTRA Non-EEA | D42: INTRA Non-EEA | O42: =SUM(E42:N42) -> 0
A43: =$G$3&$D$32&D43 -> UKOCT - FDINTER | B43: INTER | D43: INTER | O43: =SUM(E43:N43) -> 0
D45: AFT | E45: 1 | F45: 2 | G45: 3 | H45: 4 | I45: 5 | J45: 6 | K45: 7 | L45: 8 | M45: 9 | N45: 10 | O45: Total
D46: Total PV | E46: =SUM(E47:E50) -> 1047200000 | F46: =SUM(F47:F50) -> 1047200000 | G46: =SUM(G47:G50) -> 0 | H46: =SUM(H47:H50) -> 0 | I46: =SUM(I47:I50) -> 0 | J46: =SUM(J47:J50) -> 0 | K46: =SUM(K47:K50) -> 0 | L46: =SUM(L47:L50) -> 0 | ... N46: =SUM(N47:N50) -> 0 | O46: =SUM(E46:N46) -> 2094400000
D47: DOM | E47: =E53*$G9 -> 1047200000 | F47: =F53*$G9 -> 1047200000 | G47: =G53*$G9 -> 0 | H47: =H53*$G9 -> 0 | I47: =I53*$G9 -> 0 | J47: =J53*$G9 -> 0 | K47: =K53*$G9 -> 0 | L47: =L53*$G9 -> 0 | ... N47: =N53*$G9 -> 0 | O47: =SUM(E47:N47) -> 2094400000
D48: INTRA EEA | E48: =E54*$G10 -> 0 | F48: =F54*$G10 -> 0 | G48: =G54*$G10 -> 0 | H48: =H54*$G10 -> 0 | I48: =I54*$G10 -> 0 | J48: =J54*$G10 -> 0 | K48: =K54*$G10 -> 0 | L48: =L54*$G10 -> 0 | ... N48: =N54*$G10 -> 0 | O48: =SUM(E48:N48) -> 0
D49: INTRA Non-EEA | E49: =E55*$G11 -> 0 | F49: =F55*$G11 -> 0 | G49: =G55*$G11 -> 0 | H49: =H55*$G11 -> 0 | I49: =I55*$G11 -> 0 | J49: =J55*$G11 -> 0 | K49: =K55*$G11 -> 0 | L49: =L55*$G11 -> 0 | ... N49: =N55*$G11 -> 0 | O49: =SUM(E49:N49) -> 0 | R49: 1000000 | S49: 1100000 | T49: 1182500 | U49: 1241625 | V49: 1303706.2
D50: INTER | E50: =E56*$G12 -> 0 | F50: =F56*$G12 -> 0 | G50: =G56*$G12 -> 0 | H50: =H56*$G12 -> 0 | I50: =I56*$G12 -> 0 | J50: =J56*$G12 -> 0 | K50: =K56*$G12 -> 0 | L50: =L56*$G12 -> 0 | ... N50: =N56*$G12 -> 0 | O50: =SUM(E50:N50) -> 0
E51: 0.5 | R51: Choose Main and Detailed Use Case for AFT | T51: Secondary (BAI) | U51: Tertiary BAI
D52: Total Transactions | E52: =SUM(E53:E56) -> 6545000 | F52: =SUM(F53:F56) -> 6545000 | G52: =SUM(G53:G56) -> 0 | H52: =SUM(H53:H56) -> 0 | I52: =SUM(I53:I56) -> 0 | J52: =SUM(J53:J56) -> 0 | K52: =SUM(K53:K56) -> 0 | L52: =SUM(L53:L56) -> 0 | ... N52: =SUM(N53:N56) -> 0 | O52: =SUM(E52:N52) -> 13090000 | P52: =O52/SUM($O$26+$O$39+$O$52) -> 1
A53: =$G$3&$D$45&D53 -> UKAFTDOM | B53: DOM | D53: DOM | E53: 6545000 | F53: 6545000 | O53: =SUM(E53:N53) -> 13090000 | R53: A2A | S53: Wallet Loads
A54: =$G$3&$D$45&D54 -> UKAFTINTRA EEA | B54: INTRA EEA | D54: INTRA EEA | O54: =SUM(E54:N54) -> 0
A55: =$G$3&$D$45&D55 -> UKAFTINTRA Non-EEA | B55: INTRA Non-EEA | D55: INTRA Non-EEA | O55: =SUM(E55:N55) -> 0
A56: =$G$3&$D$45&D56 -> UKAFTINTER | B56: INTER | D56: INTER | O56: =SUM(E56:N56) -> 0
D58: Total | E58: 1 | F58: 2 | G58: 3 | H58: 4 | I58: 5 | J58: 6 | K58: 7 | L58: 8 | M58: 9 | N58: 10 | O58: Total
D59: Total PV | E59: =SUM(E60:E63) -> 1047200000 | F59: =SUM(F60:F63) -> 1047200000 | G59: =SUM(G60:G63) -> 0 | H59: =SUM(H60:H63) -> 0 | I59: =SUM(I60:I63) -> 0 | J59: =SUM(J60:J63) -> 0 | K59: =SUM(K60:K63) -> 0 | L59: =SUM(L60:L63) -> 0 | ... N59: =SUM(N60:N63) -> 0 | O59: =SUM(E59:N59) -> 2094400000
D60: DOM | E60: =E47+E34+E21 -> 1047200000 | F60: =F47+F34+F21 -> 1047200000 | G60: =G47+G34+G21 -> 0 | H60: =H47+H34+H21 -> 0 | I60: =I47+I34+I21 -> 0 | J60: =J47+J34+J21 -> 0 | K60: =K47+K34+K21 -> 0 | L60: =L47+L34+L21 -> 0 | ... N60: =N47+N34+N21 -> 0 | O60: =SUM(E60:N60) -> 2094400000
D61: INTRA EEA | E61: =E48+E35+E22 -> 0 | F61: =F48+F35+F22 -> 0 | G61: =G48+G35+G22 -> 0 | H61: =H48+H35+H22 -> 0 | I61: =I48+I35+I22 -> 0 | J61: =J48+J35+J22 -> 0 | K61: =K48+K35+K22 -> 0 | L61: =L48+L35+L22 -> 0 | ... N61: =N48+N35+N22 -> 0 | O61: =SUM(E61:N61) -> 0
D62: INTRA Non-EEA | E62: =E49+E36+E23 -> 0 | F62: =F49+F36+F23 -> 0 | G62: =G49+G36+G23 -> 0 | H62: =H49+H36+H23 -> 0 | I62: =I49+I36+I23 -> 0 | J62: =J49+J36+J23 -> 0 | K62: =K49+K36+K23 -> 0 | L62: =L49+L36+L23 -> 0 | ... N62: =N49+N36+N23 -> 0 | O62: =SUM(E62:N62) -> 0
D63: INTER | E63: =E50+E37+E24 -> 0 | F63: =F50+F37+F24 -> 0 | G63: =G50+G37+G24 -> 0 | H63: =H50+H37+H24 -> 0 | I63: =I50+I37+I24 -> 0 | J63: =J50+J37+J24 -> 0 | K63: =K50+K37+K24 -> 0 | L63: =L50+L37+L24 -> 0 | ... N63: =N50+N37+N24 -> 0 | O63: =SUM(E63:N63) -> 0
D65: Grand Total Transactions | E65: =SUM(E66:E69) -> 6545000 | F65: =SUM(F66:F69) -> 6545000 | G65: =SUM(G66:G69) -> 0 | H65: =SUM(H66:H69) -> 0 | I65: =SUM(I66:I69) -> 0 | J65: =SUM(J66:J69) -> 0 | K65: =SUM(K66:K69) -> 0 | L65: =SUM(L66:L69) -> 0 | ... N65: =SUM(N66:N69) -> 0 | O65: =SUM(E65:N65) -> 13090000
A66: =$G$3&$D$58&D66 -> UKTotalDOM | B66: DOM | D66: DOM | E66: =E53+E40+E27 -> 6545000 | F66: =F53+F40+F27 -> 6545000 | G66: =G53+G40+G27 -> 0 | H66: =H53+H40+H27 -> 0 | I66: =I53+I40+I27 -> 0 | J66: =J53+J40+J27 -> 0 | K66: =K53+K40+K27 -> 0 | L66: =L53+L40+L27 -> 0 | ... N66: =N53+N40+N27 -> 0 | O66: =SUM(E66:N66) -> 13090000 | P66: =O66/$O$65 -> 1
A67: =$G$3&$D$58&D67 -> UKTotalINTRA EEA | B67: INTRA EEA | D67: INTRA EEA | E67: =E54+E41+E28 -> 0 | F67: =F54+F41+F28 -> 0 | G67: =G54+G41+G28 -> 0 | H67: =H54+H41+H28 -> 0 | I67: =I54+I41+I28 -> 0 | J67: =J54+J41+J28 -> 0 | K67: =K54+K41+K28 -> 0 | L67: =L54+L41+L28 -> 0 | ... N67: =N54+N41+N28 -> 0 | O67: =SUM(E67:N67) -> 0 | P67: =O67/$O$65 -> 0
A68: =$G$3&$D$58&D68 -> UKTotalINTRA Non-EEA | B68: INTRA Non-EEA | D68: INTRA Non-EEA | E68: =E55+E42+E29 -> 0 | F68: =F55+F42+F29 -> 0 | G68: =G55+G42+G29 -> 0 | H68: =H55+H42+H29 -> 0 | I68: =I55+I42+I29 -> 0 | J68: =J55+J42+J29 -> 0 | K68: =K55+K42+K29 -> 0 | L68: =L55+L42+L29 -> 0 | ... N68: =N55+N42+N29 -> 0 | O68: =SUM(E68:N68) -> 0 | P68: =O68/$O$65 -> 0
A69: =$G$3&$D$58&D69 -> UKTotalINTER | B69: INTER | D69: INTER | E69: =E56+E43+E30 -> 0 | F69: =F56+F43+F30 -> 0 | G69: =G56+G43+G30 -> 0 | H69: =H56+H43+H30 -> 0 | I69: =I56+I43+I30 -> 0 | J69: =J56+J43+J30 -> 0 | K69: =K56+K43+K30 -> 0 | L69: =L56+L43+L30 -> 0 | ... N69: =N56+N43+N30 -> 0 | O69: =SUM(E69:N69) -> 0 | P69: =O69/$O$65 -> 0
E78: Start Qtr | F78: End Qtr | G78: Rack | H78: Rack
E79: 44562 | F79: 44926 | G79: MLP T1 | H79: Standard - EU - Instant Funding Program Tier 1
E80: 44652 | F80: 45016 | G80: MLP T2 | H80: Standard - EU - Instant Funding Program Tier 2
E81: 44743 | F81: 45107
E82: 44835 | F82: 45199 | G82: Rack | H82: Rack
E83: 44927 | F83: 45291 | G83: SAFP | H83: Standard - EU - Strategic Alliance Fee Programme
E84: 45017 | F84: 45382
E85: 45108 | F85: 45473
E86: 45200 | F86: 45565
E87: 45292 | F87: 45657
E88: 45383 | F88: 45747
E89: 45474 | F89: 45838
E90: 45566 | F90: 45930
E91: 45658 | F91: 46022
E92: 45748 | F92: 46112
E93: 45839 | F93: 46203
E94: 45931 | F94: 46295
E95: 46023 | F95: 46387
... E122: 48488 | F122: 48852
F123: 48944
F124: 49034
F125: 49125
F126: 49217
F127: 49309
F128: 49399
F129: 49490
F130: 49582
F131: 49674
F132: 49765
F133: 49856
F134: 49948
... F143: 50770
